{"ridges": [{"minutiae": [[99, 364], [100, 365]]}, {"minutiae": [[99, 364], [100, 363]]}, {"minutiae": [[99, 364], [100, 362]]}, {"minutiae": [[100, 363], [101, 364]]}, {"minutiae": [[100, 363], [100, 362]]}, {"minutiae": [[100, 365], [101, 364]]}, {"minutiae": [[100, 365], [104, 371]]}, {"minutiae": [[101, 364], [115, 371]]}, {"minutiae": [[105, 351], [106, 350]]}, {"minutiae": [[106, 349], [106, 350]]}, {"minutiae": [[106, 350], [148, 397]]}, {"minutiae": [[107, 374], [112, 379]]}, {"minutiae": [[109, 304], [119, 317]]}, {"minutiae": [[109, 321], [121, 335]]}, {"minutiae": [[109, 339], [125, 351]]}, {"minutiae": [[114, 373], [115, 371]]}, {"minutiae": [[115, 371], [117, 373]]}, {"minutiae": [[116, 294], [117, 297]]}, {"minutiae": [[116, 299], [117, 297]]}, {"minutiae": [[116, 375], [117, 373]]}, {"minutiae": [[116, 380], [121, 385]]}, {"minutiae": [[117, 297], [122, 306]]}, {"minutiae": [[117, 373], [121, 375]]}, {"minutiae": [[118, 319], [119, 317]]}, {"minutiae": [[119, 317], [137, 337]]}, {"minutiae": [[120, 306], [122, 306]]}, {"minutiae": [[120, 337], [121, 335]]}, {"minutiae": [[120, 377], [121, 375]]}, {"minutiae": [[121, 290], [122, 273]]}, {"minutiae": [[121, 335], [137, 349]]}, {"minutiae": [[121, 375], [132, 391]]}, {"minutiae": [[122, 306], [128, 314]]}, {"minutiae": [[124, 353], [125, 351]]}, {"minutiae": [[124, 360], [128, 361]]}, {"minutiae": [[125, 351], [150, 374]]}, {"minutiae": [[125, 389], [127, 391]]}, {"minutiae": [[128, 287], [177, 362]]}, {"minutiae": [[128, 361], [128, 364]]}, {"minutiae": [[128, 361], [154, 392]]}, {"minutiae": [[132, 316], [146, 337]]}, {"minutiae": [[135, 258], [135, 261]]}, {"minutiae": [[135, 261], [138, 294]]}, {"minutiae": [[135, 261], [144, 288]]}, {"minutiae": [[136, 297], [138, 294]]}, {"minutiae": [[136, 339], [137, 337]]}, {"minutiae": [[136, 351], [137, 349]]}, {"minutiae": [[137, 337], [145, 343]]}, {"minutiae": [[137, 349], [159, 371]]}, {"minutiae": [[138, 294], [161, 331]]}, {"minutiae": [[142, 253], [151, 281]]}, {"minutiae": [[143, 164], [147, 162]]}, {"minutiae": [[143, 177], [220, 139]]}, {"minutiae": [[143, 186], [177, 165]]}, {"minutiae": [[143, 195], [218, 157]]}, {"minutiae": [[143, 209], [151, 201]]}, {"minutiae": [[143, 232], [180, 188]]}, {"minutiae": [[144, 345], [145, 343]]}, {"minutiae": [[145, 343], [164, 362]]}, {"minutiae": [[147, 161], [147, 162]]}, {"minutiae": [[147, 162], [218, 132]]}, {"minutiae": [[148, 289], [169, 325]]}, {"minutiae": [[150, 284], [151, 281]]}, {"minutiae": [[150, 374], [151, 374]]}, {"minutiae": [[150, 374], [156, 387]]}, {"minutiae": [[151, 201], [185, 181]]}, {"minutiae": [[151, 201], [152, 203]]}, {"minutiae": [[151, 281], [195, 342]]}, {"minutiae": [[152, 400], [156, 402]]}, {"minutiae": [[154, 392], [154, 395]]}, {"minutiae": [[154, 392], [156, 391]]}, {"minutiae": [[156, 374], [159, 379]]}, {"minutiae": [[156, 387], [156, 391]]}, {"minutiae": [[156, 387], [162, 392]]}, {"minutiae": [[156, 391], [161, 397]]}, {"minutiae": [[156, 401], [156, 402]]}, {"minutiae": [[156, 402], [158, 404]]}, {"minutiae": [[158, 334], [160, 334]]}, {"minutiae": [[158, 373], [159, 371]]}, {"minutiae": [[158, 381], [159, 379]]}, {"minutiae": [[159, 219], [162, 286]]}, {"minutiae": [[159, 219], [203, 186]]}, {"minutiae": [[159, 219], [160, 221]]}, {"minutiae": [[159, 371], [163, 374]]}, {"minutiae": [[159, 379], [163, 383]]}, {"minutiae": [[160, 289], [161, 287]]}, {"minutiae": [[160, 334], [161, 335]]}, {"minutiae": [[160, 334], [161, 331]]}, {"minutiae": [[160, 337], [161, 335]]}, {"minutiae": [[160, 399], [161, 397]]}, {"minutiae": [[161, 287], [162, 288]]}, {"minutiae": [[161, 287], [162, 286]]}, {"minutiae": [[161, 331], [164, 334]]}, {"minutiae": [[161, 335], [167, 343]]}, {"minutiae": [[161, 397], [168, 404]]}, {"minutiae": [[162, 286], [164, 286]]}, {"minutiae": [[162, 288], [162, 289]]}, {"minutiae": [[162, 288], [167, 291]]}, {"minutiae": [[162, 385], [163, 383]]}, {"minutiae": [[163, 374], [164, 370]]}, {"minutiae": [[163, 374], [182, 398]]}, {"minutiae": [[163, 383], [182, 406]]}, {"minutiae": [[164, 362], [165, 362]]}, {"minutiae": [[164, 362], [172, 371]]}, {"minutiae": [[167, 291], [169, 299]]}, {"minutiae": [[167, 291], [181, 207]]}, {"minutiae": [[167, 343], [167, 344]]}, {"minutiae": [[167, 343], [181, 353]]}, {"minutiae": [[168, 302], [169, 299]]}, {"minutiae": [[169, 259], [189, 211]]}, {"minutiae": [[169, 259], [169, 265]]}, {"minutiae": [[169, 259], [172, 260]]}, {"minutiae": [[169, 299], [188, 325]]}, {"minutiae": [[169, 325], [194, 360]]}, {"minutiae": [[169, 325], [179, 333]]}, {"minutiae": [[172, 140], [178, 137]]}, {"minutiae": [[172, 268], [176, 286]]}, {"minutiae": [[174, 366], [177, 376]]}, {"minutiae": [[174, 376], [177, 376]]}, {"minutiae": [[175, 290], [176, 286]]}, {"minutiae": [[175, 290], [189, 317]]}, {"minutiae": [[175, 290], [177, 287]]}, {"minutiae": [[176, 142], [179, 138]]}, {"minutiae": [[176, 286], [177, 287]]}, {"minutiae": [[176, 365], [177, 362]]}, {"minutiae": [[177, 165], [205, 153]]}, {"minutiae": [[177, 165], [178, 167]]}, {"minutiae": [[177, 287], [184, 303]]}, {"minutiae": [[177, 362], [180, 364]]}, {"minutiae": [[177, 376], [180, 380]]}, {"minutiae": [[178, 137], [179, 138]]}, {"minutiae": [[178, 137], [222, 117]]}, {"minutiae": [[178, 335], [179, 333]]}, {"minutiae": [[178, 367], [180, 364]]}, {"minutiae": [[178, 384], [180, 380]]}, {"minutiae": [[179, 138], [204, 130]]}, {"minutiae": [[179, 233], [179, 244]]}, {"minutiae": [[179, 233], [200, 212]]}, {"minutiae": [[179, 233], [180, 236]]}, {"minutiae": [[179, 244], [192, 310]]}, {"minutiae": [[179, 244], [190, 233]]}, {"minutiae": [[179, 333], [188, 344]]}, {"minutiae": [[180, 355], [181, 353]]}, {"minutiae": [[180, 364], [183, 381]]}, {"minutiae": [[180, 380], [183, 381]]}, {"minutiae": [[181, 207], [202, 194]]}, {"minutiae": [[181, 207], [182, 209]]}, {"minutiae": [[181, 353], [186, 361]]}, {"minutiae": [[183, 381], [187, 387]]}, {"minutiae": [[184, 393], [190, 396]]}, {"minutiae": [[185, 181], [197, 175]]}, {"minutiae": [[185, 181], [186, 183]]}, {"minutiae": [[186, 408], [188, 410]]}, {"minutiae": [[187, 387], [190, 388]]}, {"minutiae": [[187, 387], [190, 396]]}, {"minutiae": [[189, 211], [201, 203]]}, {"minutiae": [[189, 211], [190, 213]]}, {"minutiae": [[190, 233], [194, 228]]}, {"minutiae": [[190, 233], [193, 235]]}, {"minutiae": [[190, 396], [191, 398]]}, {"minutiae": [[191, 406], [198, 414]]}, {"minutiae": [[192, 297], [194, 302]]}, {"minutiae": [[192, 310], [193, 310]]}, {"minutiae": [[192, 310], [192, 313]]}, {"minutiae": [[192, 380], [194, 380]]}, {"minutiae": [[192, 382], [195, 382]]}, {"minutiae": [[193, 235], [194, 236]]}, {"minutiae": [[193, 235], [196, 234]]}, {"minutiae": [[193, 238], [200, 298]]}, {"minutiae": [[193, 238], [194, 236]]}, {"minutiae": [[193, 238], [194, 236]]}, {"minutiae": [[193, 321], [193, 323]]}, {"minutiae": [[193, 323], [194, 326]]}, {"minutiae": [[193, 323], [195, 325]]}, {"minutiae": [[194, 228], [195, 227]]}, {"minutiae": [[194, 228], [196, 231]]}, {"minutiae": [[194, 326], [195, 325]]}, {"minutiae": [[194, 326], [195, 342]]}, {"minutiae": [[194, 360], [195, 363]]}, {"minutiae": [[194, 360], [196, 358]]}, {"minutiae": [[194, 380], [195, 363]]}, {"minutiae": [[194, 380], [195, 382]]}, {"minutiae": [[194, 389], [195, 387]]}, {"minutiae": [[194, 392], [196, 394]]}, {"minutiae": [[194, 398], [198, 401]]}, {"minutiae": [[195, 227], [197, 222]]}, {"minutiae": [[195, 227], [200, 225]]}, {"minutiae": [[195, 325], [202, 335]]}, {"minutiae": [[195, 342], [196, 343]]}, {"minutiae": [[195, 363], [197, 364]]}, {"minutiae": [[195, 382], [195, 387]]}, {"minutiae": [[195, 387], [196, 394]]}, {"minutiae": [[196, 250], [197, 267]]}, {"minutiae": [[196, 343], [196, 358]]}, {"minutiae": [[196, 343], [200, 349]]}, {"minutiae": [[196, 358], [197, 358]]}, {"minutiae": [[196, 394], [198, 401]]}, {"minutiae": [[197, 175], [226, 161]]}, {"minutiae": [[197, 175], [203, 177]]}, {"minutiae": [[197, 267], [198, 269]]}, {"minutiae": [[197, 267], [199, 266]]}, {"minutiae": [[198, 269], [203, 289]]}, {"minutiae": [[198, 269], [201, 268]]}, {"minutiae": [[198, 401], [205, 413]]}, {"minutiae": [[199, 246], [199, 248]]}, {"minutiae": [[199, 266], [201, 265]]}, {"minutiae": [[199, 266], [201, 268]]}, {"minutiae": [[200, 211], [200, 212]]}, {"minutiae": [[200, 212], [201, 212]]}, {"minutiae": [[200, 225], [200, 228]]}, {"minutiae": [[200, 225], [203, 221]]}, {"minutiae": [[200, 298], [202, 321]]}, {"minutiae": [[200, 298], [205, 305]]}, {"minutiae": [[201, 203], [206, 200]]}, {"minutiae": [[201, 203], [202, 205]]}, {"minutiae": [[201, 237], [201, 268]]}, {"minutiae": [[201, 268], [212, 287]]}, {"minutiae": [[202, 291], [203, 289]]}, {"minutiae": [[202, 321], [202, 324]]}, {"minutiae": [[202, 321], [211, 335]]}, {"minutiae": [[202, 370], [205, 369]]}, {"minutiae": [[202, 376], [205, 388]]}, {"minutiae": [[202, 417], [202, 418]]}, {"minutiae": [[203, 177], [212, 175]]}, {"minutiae": [[203, 177], [207, 182]]}, {"minutiae": [[203, 186], [208, 184]]}, {"minutiae": [[203, 186], [209, 186]]}, {"minutiae": [[203, 219], [203, 221]]}, {"minutiae": [[203, 221], [204, 222]]}, {"minutiae": [[203, 289], [213, 305]]}, {"minutiae": [[203, 359], [205, 369]]}, {"minutiae": [[204, 128], [204, 130]]}, {"minutiae": [[204, 130], [215, 127]]}, {"minutiae": [[204, 182], [207, 182]]}, {"minutiae": [[204, 222], [205, 222]]}, {"minutiae": [[204, 222], [209, 238]]}, {"minutiae": [[204, 307], [205, 305]]}, {"minutiae": [[204, 393], [205, 391]]}, {"minutiae": [[204, 397], [207, 399]]}, {"minutiae": [[204, 417], [205, 413]]}, {"minutiae": [[205, 153], [235, 159]]}, {"minutiae": [[205, 153], [206, 155]]}, {"minutiae": [[205, 305], [210, 316]]}, {"minutiae": [[205, 369], [209, 375]]}, {"minutiae": [[205, 388], [205, 391]]}, {"minutiae": [[205, 388], [212, 392]]}, {"minutiae": [[205, 391], [208, 394]]}, {"minutiae": [[205, 413], [208, 416]]}, {"minutiae": [[207, 182], [208, 184]]}, {"minutiae": [[207, 207], [211, 221]]}, {"minutiae": [[207, 352], [215, 365]]}, {"minutiae": [[207, 399], [208, 406]]}, {"minutiae": [[207, 399], [218, 408]]}, {"minutiae": [[208, 184], [209, 186]]}, {"minutiae": [[208, 200], [211, 200]]}, {"minutiae": [[208, 316], [210, 316]]}, {"minutiae": [[208, 318], [210, 318]]}, {"minutiae": [[208, 338], [209, 337]]}, {"minutiae": [[208, 338], [208, 336]]}, {"minutiae": [[208, 338], [212, 343]]}, {"minutiae": [[208, 377], [209, 375]]}, {"minutiae": [[209, 186], [222, 190]]}, {"minutiae": [[209, 238], [210, 244]]}, {"minutiae": [[209, 238], [214, 235]]}, {"minutiae": [[209, 265], [210, 244]]}, {"minutiae": [[209, 337], [208, 336]]}, {"minutiae": [[209, 337], [211, 335]]}, {"minutiae": [[209, 375], [210, 376]]}, {"minutiae": [[210, 223], [211, 221]]}, {"minutiae": [[210, 244], [214, 254]]}, {"minutiae": [[210, 269], [239, 325]]}, {"minutiae": [[210, 316], [210, 318]]}, {"minutiae": [[210, 318], [238, 356]]}, {"minutiae": [[210, 376], [211, 376]]}, {"minutiae": [[210, 376], [234, 409]]}, {"minutiae": [[210, 407], [212, 409]]}, {"minutiae": [[211, 200], [214, 206]]}, {"minutiae": [[211, 200], [213, 198]]}, {"minutiae": [[211, 221], [216, 230]]}, {"minutiae": [[211, 335], [212, 336]]}, {"minutiae": [[212, 175], [231, 167]]}, {"minutiae": [[212, 175], [216, 179]]}, {"minutiae": [[212, 192], [213, 192]]}, {"minutiae": [[212, 194], [213, 198]]}, {"minutiae": [[212, 307], [213, 305]]}, {"minutiae": [[212, 336], [213, 339]]}, {"minutiae": [[212, 336], [213, 339]]}, {"minutiae": [[212, 343], [213, 339]]}, {"minutiae": [[212, 343], [215, 349]]}, {"minutiae": [[213, 198], [214, 206]]}, {"minutiae": [[213, 305], [240, 342]]}, {"minutiae": [[214, 206], [220, 219]]}, {"minutiae": [[214, 235], [216, 230]]}, {"minutiae": [[214, 235], [221, 257]]}, {"minutiae": [[214, 398], [217, 398]]}, {"minutiae": [[215, 127], [226, 130]]}, {"minutiae": [[215, 127], [216, 129]]}, {"minutiae": [[215, 349], [218, 355]]}, {"minutiae": [[215, 349], [218, 348]]}, {"minutiae": [[215, 365], [252, 396]]}, {"minutiae": [[215, 365], [218, 367]]}, {"minutiae": [[216, 176], [216, 179]]}, {"minutiae": [[216, 179], [223, 189]]}, {"minutiae": [[216, 230], [218, 234]]}, {"minutiae": [[216, 263], [230, 290]]}, {"minutiae": [[216, 331], [216, 334]]}, {"minutiae": [[218, 338], [224, 349]]}, {"minutiae": [[218, 408], [218, 418]]}, {"minutiae": [[218, 408], [222, 408]]}, {"minutiae": [[220, 139], [222, 134]]}, {"minutiae": [[220, 139], [224, 145]]}, {"minutiae": [[220, 261], [221, 257]]}, {"minutiae": [[220, 304], [239, 325]]}, {"minutiae": [[220, 311], [222, 315]]}, {"minutiae": [[221, 257], [226, 261]]}, {"minutiae": [[221, 412], [222, 412]]}, {"minutiae": [[222, 117], [224, 120]]}, {"minutiae": [[222, 117], [228, 117]]}, {"minutiae": [[222, 190], [223, 189]]}, {"minutiae": [[222, 190], [225, 195]]}, {"minutiae": [[222, 240], [226, 231]]}, {"minutiae": [[222, 368], [232, 377]]}, {"minutiae": [[222, 408], [222, 409]]}, {"minutiae": [[222, 408], [225, 408]]}, {"minutiae": [[223, 175], [225, 175]]}, {"minutiae": [[223, 189], [226, 190]]}, {"minutiae": [[224, 133], [226, 130]]}, {"minutiae": [[224, 204], [226, 202]]}, {"minutiae": [[224, 349], [234, 368]]}, {"minutiae": [[224, 349], [230, 358]]}, {"minutiae": [[224, 414], [224, 418]]}, {"minutiae": [[225, 175], [228, 174]]}, {"minutiae": [[225, 175], [228, 181]]}, {"minutiae": [[225, 195], [226, 197]]}, {"minutiae": [[225, 195], [226, 190]]}, {"minutiae": [[226, 130], [236, 143]]}, {"minutiae": [[226, 146], [228, 148]]}, {"minutiae": [[226, 190], [227, 190]]}, {"minutiae": [[226, 197], [226, 202]]}, {"minutiae": [[226, 197], [228, 196]]}, {"minutiae": [[226, 202], [229, 213]]}, {"minutiae": [[226, 231], [229, 213]]}, {"minutiae": [[226, 231], [228, 234]]}, {"minutiae": [[226, 243], [226, 251]]}, {"minutiae": [[226, 251], [227, 254]]}, {"minutiae": [[226, 251], [228, 255]]}, {"minutiae": [[226, 261], [238, 283]]}, {"minutiae": [[226, 261], [227, 259]]}, {"minutiae": [[226, 392], [242, 403]]}, {"minutiae": [[227, 254], [228, 255]]}, {"minutiae": [[227, 254], [227, 259]]}, {"minutiae": [[227, 259], [228, 255]]}, {"minutiae": [[228, 117], [238, 116]]}, {"minutiae": [[228, 117], [234, 131]]}, {"minutiae": [[228, 239], [228, 240]]}, {"minutiae": [[229, 213], [233, 211]]}, {"minutiae": [[229, 243], [229, 244]]}, {"minutiae": [[230, 172], [233, 171]]}, {"minutiae": [[230, 186], [234, 187]]}, {"minutiae": [[230, 221], [230, 223]]}, {"minutiae": [[230, 240], [235, 237]]}, {"minutiae": [[230, 290], [236, 298]]}, {"minutiae": [[230, 290], [234, 289]]}, {"minutiae": [[230, 412], [233, 412]]}, {"minutiae": [[231, 167], [234, 165]]}, {"minutiae": [[231, 167], [233, 171]]}, {"minutiae": [[232, 204], [235, 209]]}, {"minutiae": [[232, 286], [234, 289]]}, {"minutiae": [[232, 377], [232, 380]]}, {"minutiae": [[232, 377], [246, 382]]}, {"minutiae": [[233, 105], [242, 106]]}, {"minutiae": [[233, 171], [240, 191]]}, {"minutiae": [[233, 211], [235, 209]]}, {"minutiae": [[233, 211], [235, 237]]}, {"minutiae": [[233, 412], [234, 413]]}, {"minutiae": [[233, 412], [234, 409]]}, {"minutiae": [[233, 417], [234, 413]]}, {"minutiae": [[234, 191], [239, 209]]}, {"minutiae": [[234, 263], [237, 267]]}, {"minutiae": [[234, 289], [235, 291]]}, {"minutiae": [[234, 293], [235, 291]]}, {"minutiae": [[234, 367], [234, 368]]}, {"minutiae": [[234, 368], [235, 369]]}, {"minutiae": [[234, 371], [235, 369]]}, {"minutiae": [[234, 409], [236, 410]]}, {"minutiae": [[234, 413], [241, 417]]}, {"minutiae": [[235, 159], [237, 155]]}, {"minutiae": [[235, 159], [244, 178]]}, {"minutiae": [[235, 209], [238, 210]]}, {"minutiae": [[235, 237], [235, 247]]}, {"minutiae": [[235, 247], [237, 267]]}, {"minutiae": [[235, 247], [238, 246]]}, {"minutiae": [[235, 291], [246, 300]]}, {"minutiae": [[235, 369], [240, 374]]}, {"minutiae": [[236, 143], [237, 155]]}, {"minutiae": [[236, 143], [238, 144]]}, {"minutiae": [[236, 298], [237, 297]]}, {"minutiae": [[236, 298], [256, 336]]}, {"minutiae": [[237, 155], [240, 156]]}, {"minutiae": [[237, 267], [238, 269]]}, {"minutiae": [[237, 271], [238, 269]]}, {"minutiae": [[238, 100], [238, 101]]}, {"minutiae": [[238, 110], [240, 112]]}, {"minutiae": [[238, 116], [240, 112]]}, {"minutiae": [[238, 116], [242, 127]]}, {"minutiae": [[238, 210], [239, 209]]}, {"minutiae": [[238, 210], [246, 227]]}, {"minutiae": [[238, 269], [248, 281]]}, {"minutiae": [[238, 283], [238, 286]]}, {"minutiae": [[238, 283], [247, 288]]}, {"minutiae": [[238, 356], [253, 381]]}, {"minutiae": [[238, 356], [246, 356]]}, {"minutiae": [[239, 209], [242, 210]]}, {"minutiae": [[239, 325], [274, 364]]}, {"minutiae": [[240, 112], [245, 112]]}, {"minutiae": [[240, 257], [241, 255]]}, {"minutiae": [[240, 408], [243, 408]]}, {"minutiae": [[241, 255], [246, 252]]}, {"minutiae": [[241, 255], [242, 264]]}, {"minutiae": [[242, 127], [246, 150]]}, {"minutiae": [[242, 127], [248, 132]]}, {"minutiae": [[242, 403], [243, 408]]}, {"minutiae": [[242, 403], [252, 404]]}, {"minutiae": [[243, 250], [245, 250]]}, {"minutiae": [[243, 408], [250, 414]]}, {"minutiae": [[244, 189], [247, 199]]}, {"minutiae": [[244, 303], [248, 309]]}, {"minutiae": [[244, 341], [247, 345]]}, {"minutiae": [[245, 112], [245, 115]]}, {"minutiae": [[245, 112], [248, 112]]}, {"minutiae": [[245, 250], [246, 227]]}, {"minutiae": [[245, 250], [246, 252]]}, {"minutiae": [[246, 136], [249, 136]]}, {"minutiae": [[246, 157], [247, 163]]}, {"minutiae": [[246, 165], [247, 163]]}, {"minutiae": [[246, 227], [247, 220]]}, {"minutiae": [[246, 252], [247, 256]]}, {"minutiae": [[246, 347], [247, 345]]}, {"minutiae": [[246, 350], [247, 355]]}, {"minutiae": [[246, 356], [247, 355]]}, {"minutiae": [[246, 356], [263, 379]]}, {"minutiae": [[246, 382], [248, 382]]}, {"minutiae": [[246, 382], [248, 382]]}, {"minutiae": [[247, 90], [250, 104]]}, {"minutiae": [[247, 163], [250, 165]]}, {"minutiae": [[247, 199], [247, 209]]}, {"minutiae": [[247, 199], [248, 201]]}, {"minutiae": [[247, 209], [257, 231]]}, {"minutiae": [[247, 209], [248, 206]]}, {"minutiae": [[247, 264], [261, 279]]}, {"minutiae": [[247, 288], [248, 281]]}, {"minutiae": [[247, 288], [249, 291]]}, {"minutiae": [[247, 345], [252, 349]]}, {"minutiae": [[247, 355], [254, 358]]}, {"minutiae": [[248, 117], [248, 132]]}, {"minutiae": [[248, 132], [249, 136]]}, {"minutiae": [[248, 191], [249, 189]]}, {"minutiae": [[248, 281], [263, 290]]}, {"minutiae": [[248, 293], [249, 291]]}, {"minutiae": [[248, 382], [253, 381]]}, {"minutiae": [[249, 108], [249, 109]]}, {"minutiae": [[249, 136], [251, 141]]}, {"minutiae": [[249, 189], [250, 176]]}, {"minutiae": [[249, 189], [256, 200]]}, {"minutiae": [[249, 291], [264, 306]]}, {"minutiae": [[250, 165], [250, 176]]}, {"minutiae": [[250, 165], [253, 163]]}, {"minutiae": [[250, 176], [252, 176]]}, {"minutiae": [[250, 298], [253, 303]]}, {"minutiae": [[250, 414], [254, 412]]}, {"minutiae": [[250, 414], [253, 417]]}, {"minutiae": [[251, 141], [254, 152]]}, {"minutiae": [[251, 141], [254, 142]]}, {"minutiae": [[252, 390], [264, 394]]}, {"minutiae": [[252, 404], [256, 403]]}, {"minutiae": [[252, 404], [255, 405]]}, {"minutiae": [[253, 86], [256, 88]]}, {"minutiae": [[253, 163], [254, 159]]}, {"minutiae": [[253, 163], [254, 166]]}, {"minutiae": [[253, 303], [254, 300]]}, {"minutiae": [[253, 303], [258, 308]]}, {"minutiae": [[253, 311], [264, 331]]}, {"minutiae": [[253, 381], [257, 384]]}, {"minutiae": [[254, 152], [254, 155]]}, {"minutiae": [[254, 152], [257, 151]]}, {"minutiae": [[254, 155], [254, 159]]}, {"minutiae": [[254, 155], [254, 159]]}, {"minutiae": [[254, 243], [256, 257]]}, {"minutiae": [[254, 358], [256, 361]]}, {"minutiae": [[254, 358], [258, 359]]}, {"minutiae": [[255, 405], [276, 407]]}, {"minutiae": [[255, 405], [256, 403]]}, {"minutiae": [[256, 88], [258, 132]]}, {"minutiae": [[256, 88], [258, 88]]}, {"minutiae": [[256, 200], [286, 229]]}, {"minutiae": [[256, 200], [258, 190]]}, {"minutiae": [[256, 234], [257, 231]]}, {"minutiae": [[256, 257], [256, 269]]}, {"minutiae": [[256, 257], [258, 259]]}, {"minutiae": [[256, 361], [272, 381]]}, {"minutiae": [[256, 361], [258, 359]]}, {"minutiae": [[256, 400], [259, 401]]}, {"minutiae": [[256, 403], [259, 401]]}, {"minutiae": [[257, 132], [258, 132]]}, {"minutiae": [[257, 190], [258, 190]]}, {"minutiae": [[257, 231], [260, 233]]}, {"minutiae": [[257, 312], [278, 330]]}, {"minutiae": [[257, 384], [278, 390]]}, {"minutiae": [[257, 384], [263, 381]]}, {"minutiae": [[258, 88], [265, 100]]}, {"minutiae": [[258, 88], [270, 91]]}, {"minutiae": [[258, 132], [262, 143]]}, {"minutiae": [[258, 190], [260, 187]]}, {"minutiae": [[258, 259], [262, 257]]}, {"minutiae": [[258, 259], [268, 274]]}, {"minutiae": [[258, 359], [268, 366]]}, {"minutiae": [[259, 401], [287, 392]]}, {"minutiae": [[260, 172], [260, 187]]}, {"minutiae": [[260, 187], [262, 188]]}, {"minutiae": [[260, 220], [262, 220]]}, {"minutiae": [[260, 233], [260, 241]]}, {"minutiae": [[260, 233], [262, 234]]}, {"minutiae": [[260, 281], [261, 279]]}, {"minutiae": [[260, 334], [272, 352]]}, {"minutiae": [[261, 279], [311, 281]]}, {"minutiae": [[262, 143], [262, 146]]}, {"minutiae": [[262, 143], [269, 156]]}, {"minutiae": [[262, 220], [263, 220]]}, {"minutiae": [[262, 220], [286, 229]]}, {"minutiae": [[262, 257], [264, 252]]}, {"minutiae": [[262, 257], [264, 260]]}, {"minutiae": [[263, 198], [294, 217]]}, {"minutiae": [[263, 290], [291, 309]]}, {"minutiae": [[263, 290], [268, 293]]}, {"minutiae": [[263, 334], [264, 331]]}, {"minutiae": [[263, 379], [263, 381]]}, {"minutiae": [[263, 379], [264, 376]]}, {"minutiae": [[263, 381], [272, 381]]}, {"minutiae": [[264, 114], [273, 117]]}, {"minutiae": [[264, 118], [275, 131]]}, {"minutiae": [[264, 126], [267, 133]]}, {"minutiae": [[264, 151], [264, 152]]}, {"minutiae": [[264, 252], [280, 248]]}, {"minutiae": [[264, 252], [277, 251]]}, {"minutiae": [[264, 260], [270, 269]]}, {"minutiae": [[264, 260], [292, 275]]}, {"minutiae": [[264, 306], [270, 318]]}, {"minutiae": [[264, 306], [270, 307]]}, {"minutiae": [[264, 331], [267, 333]]}, {"minutiae": [[265, 100], [270, 108]]}, {"minutiae": [[265, 100], [278, 102]]}, {"minutiae": [[265, 163], [270, 178]]}, {"minutiae": [[265, 179], [268, 189]]}, {"minutiae": [[265, 235], [270, 234]]}, {"minutiae": [[266, 136], [267, 133]]}, {"minutiae": [[266, 159], [269, 156]]}, {"minutiae": [[267, 133], [275, 148]]}, {"minutiae": [[267, 333], [268, 334]]}, {"minutiae": [[267, 333], [267, 336]]}, {"minutiae": [[267, 336], [268, 334]]}, {"minutiae": [[267, 336], [279, 349]]}, {"minutiae": [[268, 195], [270, 198]]}, {"minutiae": [[268, 274], [268, 276]]}, {"minutiae": [[268, 274], [278, 277]]}, {"minutiae": [[268, 334], [289, 345]]}, {"minutiae": [[269, 156], [275, 167]]}, {"minutiae": [[269, 310], [270, 311]]}, {"minutiae": [[270, 91], [277, 89]]}, {"minutiae": [[270, 91], [277, 95]]}, {"minutiae": [[270, 108], [272, 112]]}, {"minutiae": [[270, 108], [279, 111]]}, {"minutiae": [[270, 178], [275, 191]]}, {"minutiae": [[270, 178], [276, 182]]}, {"minutiae": [[270, 290], [307, 295]]}, {"minutiae": [[270, 311], [272, 310]]}, {"minutiae": [[270, 311], [287, 317]]}, {"minutiae": [[271, 298], [274, 298]]}, {"minutiae": [[272, 119], [273, 117]]}, {"minutiae": [[272, 170], [275, 167]]}, {"minutiae": [[272, 296], [274, 298]]}, {"minutiae": [[272, 352], [272, 355]]}, {"minutiae": [[272, 352], [278, 350]]}, {"minutiae": [[272, 381], [276, 382]]}, {"minutiae": [[273, 117], [282, 123]]}, {"minutiae": [[273, 320], [287, 325]]}, {"minutiae": [[274, 136], [275, 131]]}, {"minutiae": [[274, 256], [281, 260]]}, {"minutiae": [[274, 298], [287, 304]]}, {"minutiae": [[274, 364], [304, 382]]}, {"minutiae": [[274, 364], [276, 363]]}, {"minutiae": [[275, 131], [282, 136]]}, {"minutiae": [[275, 148], [276, 152]]}, {"minutiae": [[275, 148], [280, 147]]}, {"minutiae": [[275, 167], [280, 174]]}, {"minutiae": [[275, 191], [277, 185]]}, {"minutiae": [[275, 191], [278, 193]]}, {"minutiae": [[275, 239], [310, 244]]}, {"minutiae": [[275, 358], [280, 362]]}, {"minutiae": [[275, 372], [290, 380]]}, {"minutiae": [[276, 152], [277, 155]]}, {"minutiae": [[276, 152], [280, 152]]}, {"minutiae": [[276, 182], [277, 185]]}, {"minutiae": [[276, 182], [279, 183]]}, {"minutiae": [[276, 379], [277, 380]]}, {"minutiae": [[276, 382], [277, 380]]}, {"minutiae": [[276, 382], [287, 383]]}, {"minutiae": [[276, 407], [277, 406]]}, {"minutiae": [[276, 407], [278, 411]]}, {"minutiae": [[277, 89], [285, 95]]}, {"minutiae": [[277, 89], [281, 86]]}, {"minutiae": [[277, 155], [281, 153]]}, {"minutiae": [[277, 155], [283, 163]]}, {"minutiae": [[277, 185], [279, 183]]}, {"minutiae": [[277, 250], [277, 251]]}, {"minutiae": [[277, 251], [279, 250]]}, {"minutiae": [[277, 380], [280, 379]]}, {"minutiae": [[277, 406], [288, 402]]}, {"minutiae": [[277, 406], [288, 404]]}, {"minutiae": [[278, 102], [278, 103]]}, {"minutiae": [[278, 102], [291, 108]]}, {"minutiae": [[278, 113], [279, 111]]}, {"minutiae": [[278, 193], [279, 192]]}, {"minutiae": [[278, 193], [279, 195]]}, {"minutiae": [[278, 262], [281, 260]]}, {"minutiae": [[278, 277], [278, 280]]}, {"minutiae": [[278, 277], [292, 275]]}, {"minutiae": [[278, 350], [279, 349]]}, {"minutiae": [[278, 350], [302, 361]]}, {"minutiae": [[279, 111], [285, 115]]}, {"minutiae": [[279, 183], [289, 191]]}, {"minutiae": [[279, 195], [281, 203]]}, {"minutiae": [[279, 195], [282, 198]]}, {"minutiae": [[279, 250], [280, 248]]}, {"minutiae": [[279, 250], [286, 252]]}, {"minutiae": [[279, 349], [286, 350]]}, {"minutiae": [[280, 96], [285, 95]]}, {"minutiae": [[280, 147], [282, 136]]}, {"minutiae": [[280, 147], [280, 152]]}, {"minutiae": [[280, 152], [281, 153]]}, {"minutiae": [[280, 248], [306, 250]]}, {"minutiae": [[281, 153], [290, 158]]}, {"minutiae": [[281, 203], [282, 198]]}, {"minutiae": [[281, 203], [294, 217]]}, {"minutiae": [[281, 260], [290, 260]]}, {"minutiae": [[282, 136], [288, 146]]}, {"minutiae": [[282, 198], [283, 198]]}, {"minutiae": [[282, 330], [286, 333]]}, {"minutiae": [[283, 163], [294, 186]]}, {"minutiae": [[283, 163], [291, 164]]}, {"minutiae": [[283, 391], [287, 392]]}, {"minutiae": [[284, 117], [285, 115]]}, {"minutiae": [[285, 95], [301, 98]]}, {"minutiae": [[285, 115], [287, 117]]}, {"minutiae": [[285, 121], [294, 129]]}, {"minutiae": [[285, 334], [286, 333]]}, {"minutiae": [[286, 229], [308, 232]]}, {"minutiae": [[286, 319], [287, 317]]}, {"minutiae": [[286, 333], [295, 340]]}, {"minutiae": [[287, 89], [294, 86]]}, {"minutiae": [[287, 117], [335, 129]]}, {"minutiae": [[287, 117], [288, 119]]}, {"minutiae": [[287, 304], [291, 309]]}, {"minutiae": [[287, 304], [313, 303]]}, {"minutiae": [[287, 317], [292, 318]]}, {"minutiae": [[287, 325], [290, 324]]}, {"minutiae": [[287, 325], [300, 334]]}, {"minutiae": [[287, 383], [290, 381]]}, {"minutiae": [[287, 383], [290, 384]]}, {"minutiae": [[287, 392], [299, 396]]}, {"minutiae": [[288, 195], [289, 191]]}, {"minutiae": [[288, 347], [289, 345]]}, {"minutiae": [[288, 362], [295, 367]]}, {"minutiae": [[288, 402], [288, 404]]}, {"minutiae": [[288, 402], [292, 402]]}, {"minutiae": [[288, 404], [290, 404]]}, {"minutiae": [[289, 191], [304, 213]]}, {"minutiae": [[289, 199], [289, 202]]}, {"minutiae": [[289, 345], [299, 348]]}, {"minutiae": [[290, 141], [291, 139]]}, {"minutiae": [[290, 150], [290, 152]]}, {"minutiae": [[290, 158], [291, 164]]}, {"minutiae": [[290, 158], [319, 185]]}, {"minutiae": [[290, 260], [291, 262]]}, {"minutiae": [[290, 260], [293, 257]]}, {"minutiae": [[290, 380], [290, 381]]}, {"minutiae": [[290, 380], [291, 382]]}, {"minutiae": [[290, 381], [291, 382]]}, {"minutiae": [[291, 108], [292, 111]]}, {"minutiae": [[291, 108], [318, 110]]}, {"minutiae": [[291, 135], [291, 139]]}, {"minutiae": [[291, 139], [297, 145]]}, {"minutiae": [[291, 164], [295, 169]]}, {"minutiae": [[291, 262], [293, 265]]}, {"minutiae": [[291, 262], [293, 265]]}, {"minutiae": [[291, 309], [293, 310]]}, {"minutiae": [[292, 100], [301, 99]]}, {"minutiae": [[292, 254], [293, 257]]}, {"minutiae": [[292, 275], [297, 276]]}, {"minutiae": [[292, 313], [293, 310]]}, {"minutiae": [[292, 318], [292, 319]]}, {"minutiae": [[292, 318], [294, 318]]}, {"minutiae": [[293, 257], [320, 252]]}, {"minutiae": [[293, 265], [307, 265]]}, {"minutiae": [[293, 310], [312, 312]]}, {"minutiae": [[294, 126], [294, 129]]}, {"minutiae": [[294, 129], [304, 143]]}, {"minutiae": [[294, 217], [295, 218]]}, {"minutiae": [[294, 318], [294, 319]]}, {"minutiae": [[294, 318], [298, 318]]}, {"minutiae": [[295, 169], [303, 199]]}, {"minutiae": [[295, 169], [309, 178]]}, {"minutiae": [[295, 218], [296, 222]]}, {"minutiae": [[295, 218], [305, 219]]}, {"minutiae": [[295, 340], [299, 348]]}, {"minutiae": [[295, 340], [300, 341]]}, {"minutiae": [[296, 86], [303, 89]]}, {"minutiae": [[296, 147], [297, 145]]}, {"minutiae": [[296, 404], [299, 396]]}, {"minutiae": [[297, 145], [306, 152]]}, {"minutiae": [[297, 276], [300, 278]]}, {"minutiae": [[297, 276], [320, 272]]}, {"minutiae": [[297, 322], [309, 329]]}, {"minutiae": [[298, 154], [306, 159]]}, {"minutiae": [[298, 318], [299, 320]]}, {"minutiae": [[298, 318], [317, 320]]}, {"minutiae": [[299, 348], [320, 358]]}, {"minutiae": [[299, 396], [306, 396]]}, {"minutiae": [[300, 198], [303, 199]]}, {"minutiae": [[300, 333], [300, 334]]}, {"minutiae": [[300, 334], [310, 341]]}, {"minutiae": [[300, 368], [310, 376]]}, {"minutiae": [[300, 382], [304, 382]]}, {"minutiae": [[301, 98], [301, 99]]}, {"minutiae": [[301, 98], [306, 94]]}, {"minutiae": [[301, 99], [318, 110]]}, {"minutiae": [[301, 362], [302, 361]]}, {"minutiae": [[302, 361], [304, 361]]}, {"minutiae": [[303, 89], [304, 90]]}, {"minutiae": [[303, 89], [304, 88]]}, {"minutiae": [[303, 199], [311, 205]]}, {"minutiae": [[303, 291], [307, 291]]}, {"minutiae": [[304, 84], [304, 88]]}, {"minutiae": [[304, 88], [305, 89]]}, {"minutiae": [[304, 90], [305, 89]]}, {"minutiae": [[304, 90], [306, 94]]}, {"minutiae": [[304, 213], [305, 219]]}, {"minutiae": [[304, 213], [307, 213]]}, {"minutiae": [[304, 361], [304, 364]]}, {"minutiae": [[304, 361], [322, 370]]}, {"minutiae": [[304, 382], [316, 404]]}, {"minutiae": [[305, 89], [308, 90]]}, {"minutiae": [[305, 130], [306, 131]]}, {"minutiae": [[305, 219], [308, 223]]}, {"minutiae": [[306, 94], [316, 97]]}, {"minutiae": [[306, 131], [309, 130]]}, {"minutiae": [[306, 131], [307, 133]]}, {"minutiae": [[306, 135], [307, 133]]}, {"minutiae": [[306, 156], [306, 159]]}, {"minutiae": [[306, 159], [310, 161]]}, {"minutiae": [[306, 396], [307, 396]]}, {"minutiae": [[306, 396], [307, 404]]}, {"minutiae": [[307, 133], [309, 135]]}, {"minutiae": [[307, 265], [322, 254]]}, {"minutiae": [[307, 265], [343, 247]]}, {"minutiae": [[307, 291], [307, 295]]}, {"minutiae": [[307, 291], [343, 279]]}, {"minutiae": [[307, 295], [342, 290]]}, {"minutiae": [[308, 137], [309, 135]]}, {"minutiae": [[308, 331], [309, 329]]}, {"minutiae": [[309, 135], [314, 142]]}, {"minutiae": [[309, 178], [314, 196]]}, {"minutiae": [[309, 178], [311, 179]]}, {"minutiae": [[309, 244], [310, 244]]}, {"minutiae": [[309, 329], [316, 337]]}, {"minutiae": [[310, 156], [312, 159]]}, {"minutiae": [[310, 161], [312, 159]]}, {"minutiae": [[310, 161], [317, 166]]}, {"minutiae": [[310, 197], [311, 205]]}, {"minutiae": [[310, 244], [314, 247]]}, {"minutiae": [[310, 341], [314, 346]]}, {"minutiae": [[310, 341], [312, 342]]}, {"minutiae": [[311, 205], [315, 211]]}, {"minutiae": [[311, 236], [312, 236]]}, {"minutiae": [[311, 281], [328, 276]]}, {"minutiae": [[311, 281], [314, 282]]}, {"minutiae": [[311, 380], [314, 380]]}, {"minutiae": [[312, 128], [316, 128]]}, {"minutiae": [[312, 159], [316, 158]]}, {"minutiae": [[312, 216], [314, 219]]}, {"minutiae": [[312, 312], [313, 313]]}, {"minutiae": [[312, 312], [317, 311]]}, {"minutiae": [[313, 83], [316, 87]]}, {"minutiae": [[313, 303], [336, 300]]}, {"minutiae": [[313, 303], [314, 305]]}, {"minutiae": [[313, 313], [317, 311]]}, {"minutiae": [[313, 313], [319, 317]]}, {"minutiae": [[314, 142], [327, 161]]}, {"minutiae": [[314, 142], [324, 147]]}, {"minutiae": [[314, 219], [315, 211]]}, {"minutiae": [[314, 219], [318, 233]]}, {"minutiae": [[314, 247], [314, 250]]}, {"minutiae": [[314, 247], [319, 248]]}, {"minutiae": [[314, 330], [327, 331]]}, {"minutiae": [[314, 344], [314, 346]]}, {"minutiae": [[314, 346], [318, 349]]}, {"minutiae": [[315, 136], [326, 147]]}, {"minutiae": [[315, 211], [321, 215]]}, {"minutiae": [[316, 97], [320, 94]]}, {"minutiae": [[316, 97], [322, 101]]}, {"minutiae": [[316, 190], [318, 198]]}, {"minutiae": [[316, 198], [318, 198]]}, {"minutiae": [[316, 235], [318, 233]]}, {"minutiae": [[316, 308], [319, 309]]}, {"minutiae": [[316, 326], [318, 323]]}, {"minutiae": [[316, 373], [321, 378]]}, {"minutiae": [[317, 166], [327, 179]]}, {"minutiae": [[317, 166], [325, 169]]}, {"minutiae": [[317, 311], [319, 309]]}, {"minutiae": [[317, 320], [318, 323]]}, {"minutiae": [[317, 320], [319, 317]]}, {"minutiae": [[317, 350], [318, 349]]}, {"minutiae": [[317, 380], [319, 381]]}, {"minutiae": [[318, 110], [346, 128]]}, {"minutiae": [[318, 187], [319, 185]]}, {"minutiae": [[318, 198], [323, 212]]}, {"minutiae": [[318, 233], [324, 238]]}, {"minutiae": [[318, 240], [318, 243]]}, {"minutiae": [[318, 323], [322, 324]]}, {"minutiae": [[318, 349], [328, 350]]}, {"minutiae": [[318, 389], [322, 394]]}, {"minutiae": [[319, 185], [322, 186]]}, {"minutiae": [[319, 248], [320, 249]]}, {"minutiae": [[319, 248], [321, 248]]}, {"minutiae": [[319, 309], [331, 310]]}, {"minutiae": [[319, 317], [339, 316]]}, {"minutiae": [[319, 381], [327, 395]]}, {"minutiae": [[319, 381], [321, 378]]}, {"minutiae": [[320, 132], [326, 132]]}, {"minutiae": [[320, 249], [321, 248]]}, {"minutiae": [[320, 249], [320, 252]]}, {"minutiae": [[320, 252], [321, 253]]}, {"minutiae": [[320, 342], [324, 344]]}, {"minutiae": [[320, 354], [320, 358]]}, {"minutiae": [[320, 358], [325, 360]]}, {"minutiae": [[321, 215], [323, 217]]}, {"minutiae": [[321, 215], [323, 212]]}, {"minutiae": [[321, 253], [322, 254]]}, {"minutiae": [[321, 253], [322, 250]]}, {"minutiae": [[321, 378], [328, 379]]}, {"minutiae": [[322, 87], [323, 85]]}, {"minutiae": [[322, 101], [322, 104]]}, {"minutiae": [[322, 101], [333, 107]]}, {"minutiae": [[322, 185], [322, 186]]}, {"minutiae": [[322, 186], [329, 245]]}, {"minutiae": [[322, 254], [329, 247]]}, {"minutiae": [[322, 401], [324, 399]]}, {"minutiae": [[323, 83], [323, 85]]}, {"minutiae": [[323, 85], [324, 87]]}, {"minutiae": [[323, 212], [323, 217]]}, {"minutiae": [[323, 217], [324, 238]]}, {"minutiae": [[324, 147], [328, 149]]}, {"minutiae": [[324, 147], [326, 147]]}, {"minutiae": [[324, 171], [325, 169]]}, {"minutiae": [[324, 238], [328, 246]]}, {"minutiae": [[325, 92], [332, 97]]}, {"minutiae": [[325, 169], [341, 208]]}, {"minutiae": [[325, 360], [326, 362]]}, {"minutiae": [[325, 360], [367, 355]]}, {"minutiae": [[326, 132], [336, 143]]}, {"minutiae": [[326, 132], [334, 134]]}, {"minutiae": [[326, 147], [328, 149]]}, {"minutiae": [[326, 163], [327, 161]]}, {"minutiae": [[326, 338], [333, 341]]}, {"minutiae": [[327, 161], [335, 163]]}, {"minutiae": [[327, 179], [329, 182]]}, {"minutiae": [[327, 179], [329, 182]]}, {"minutiae": [[327, 331], [410, 297]]}, {"minutiae": [[327, 331], [328, 333]]}, {"minutiae": [[327, 364], [335, 367]]}, {"minutiae": [[328, 149], [331, 150]]}, {"minutiae": [[328, 246], [329, 247]]}, {"minutiae": [[328, 246], [329, 245]]}, {"minutiae": [[328, 276], [330, 272]]}, {"minutiae": [[328, 276], [343, 269]]}, {"minutiae": [[328, 350], [328, 351]]}, {"minutiae": [[328, 350], [358, 352]]}, {"minutiae": [[328, 370], [333, 370]]}, {"minutiae": [[328, 379], [335, 382]]}, {"minutiae": [[328, 379], [334, 383]]}, {"minutiae": [[329, 182], [332, 187]]}, {"minutiae": [[329, 245], [330, 246]]}, {"minutiae": [[329, 247], [330, 246]]}, {"minutiae": [[330, 246], [332, 249]]}, {"minutiae": [[331, 83], [334, 84]]}, {"minutiae": [[331, 150], [333, 152]]}, {"minutiae": [[331, 150], [335, 150]]}, {"minutiae": [[331, 310], [336, 304]]}, {"minutiae": [[331, 310], [341, 311]]}, {"minutiae": [[332, 111], [333, 107]]}, {"minutiae": [[332, 187], [336, 195]]}, {"minutiae": [[332, 187], [336, 195]]}, {"minutiae": [[332, 343], [333, 341]]}, {"minutiae": [[332, 390], [334, 392]]}, {"minutiae": [[333, 107], [339, 110]]}, {"minutiae": [[333, 152], [347, 160]]}, {"minutiae": [[333, 152], [335, 150]]}, {"minutiae": [[333, 341], [335, 342]]}, {"minutiae": [[333, 370], [335, 367]]}, {"minutiae": [[333, 370], [340, 374]]}, {"minutiae": [[334, 93], [342, 90]]}, {"minutiae": [[334, 131], [335, 129]]}, {"minutiae": [[334, 267], [343, 259]]}, {"minutiae": [[334, 333], [334, 334]]}, {"minutiae": [[334, 345], [335, 343]]}, {"minutiae": [[334, 383], [335, 382]]}, {"minutiae": [[334, 383], [336, 390]]}, {"minutiae": [[335, 129], [338, 131]]}, {"minutiae": [[335, 150], [341, 149]]}, {"minutiae": [[335, 163], [336, 166]]}, {"minutiae": [[335, 163], [338, 162]]}, {"minutiae": [[335, 342], [335, 343]]}, {"minutiae": [[335, 342], [351, 336]]}, {"minutiae": [[335, 343], [374, 347]]}, {"minutiae": [[335, 367], [347, 367]]}, {"minutiae": [[335, 382], [336, 382]]}, {"minutiae": [[336, 143], [336, 146]]}, {"minutiae": [[336, 143], [342, 148]]}, {"minutiae": [[336, 195], [340, 207]]}, {"minutiae": [[336, 300], [337, 299]]}, {"minutiae": [[336, 300], [336, 304]]}, {"minutiae": [[336, 304], [341, 302]]}, {"minutiae": [[336, 382], [338, 380]]}, {"minutiae": [[336, 382], [338, 385]]}, {"minutiae": [[337, 299], [342, 290]]}, {"minutiae": [[337, 299], [341, 302]]}, {"minutiae": [[338, 88], [341, 83]]}, {"minutiae": [[338, 131], [347, 145]]}, {"minutiae": [[338, 131], [346, 132]]}, {"minutiae": [[338, 328], [344, 328]]}, {"minutiae": [[338, 336], [351, 336]]}, {"minutiae": [[338, 380], [340, 374]]}, {"minutiae": [[338, 380], [350, 377]]}, {"minutiae": [[339, 110], [340, 113]]}, {"minutiae": [[339, 110], [341, 112]]}, {"minutiae": [[339, 217], [343, 229]]}, {"minutiae": [[339, 316], [341, 311]]}, {"minutiae": [[339, 316], [401, 277]]}, {"minutiae": [[340, 113], [341, 114]]}, {"minutiae": [[340, 113], [341, 112]]}, {"minutiae": [[340, 204], [340, 207]]}, {"minutiae": [[340, 207], [341, 208]]}, {"minutiae": [[340, 374], [347, 367]]}, {"minutiae": [[341, 112], [350, 114]]}, {"minutiae": [[341, 149], [342, 148]]}, {"minutiae": [[341, 149], [349, 154]]}, {"minutiae": [[341, 163], [350, 172]]}, {"minutiae": [[341, 208], [343, 229]]}, {"minutiae": [[341, 302], [356, 291]]}, {"minutiae": [[341, 311], [346, 310]]}, {"minutiae": [[342, 128], [346, 128]]}, {"minutiae": [[342, 148], [347, 145]]}, {"minutiae": [[342, 290], [355, 278]]}, {"minutiae": [[342, 392], [345, 391]]}, {"minutiae": [[343, 102], [344, 102]]}, {"minutiae": [[343, 229], [343, 247]]}, {"minutiae": [[343, 247], [344, 249]]}, {"minutiae": [[343, 259], [350, 252]]}, {"minutiae": [[343, 259], [344, 261]]}, {"minutiae": [[343, 269], [355, 261]]}, {"minutiae": [[343, 269], [344, 271]]}, {"minutiae": [[343, 279], [354, 272]]}, {"minutiae": [[343, 279], [344, 281]]}, {"minutiae": [[344, 102], [359, 85]]}, {"minutiae": [[344, 102], [350, 110]]}, {"minutiae": [[345, 386], [346, 386]]}, {"minutiae": [[345, 391], [346, 392]]}, {"minutiae": [[345, 391], [346, 386]]}, {"minutiae": [[346, 110], [350, 110]]}, {"minutiae": [[346, 128], [346, 132]]}, {"minutiae": [[346, 132], [351, 137]]}, {"minutiae": [[346, 310], [346, 312]]}, {"minutiae": [[346, 310], [354, 307]]}, {"minutiae": [[346, 386], [350, 381]]}, {"minutiae": [[347, 145], [350, 146]]}, {"minutiae": [[347, 160], [348, 159]]}, {"minutiae": [[347, 160], [348, 162]]}, {"minutiae": [[347, 306], [356, 299]]}, {"minutiae": [[347, 367], [362, 367]]}, {"minutiae": [[348, 88], [352, 80]]}, {"minutiae": [[348, 159], [349, 154]]}, {"minutiae": [[348, 159], [352, 157]]}, {"minutiae": [[348, 202], [348, 204]]}, {"minutiae": [[349, 100], [361, 94]]}, {"minutiae": [[349, 154], [351, 155]]}, {"minutiae": [[350, 110], [351, 111]]}, {"minutiae": [[350, 114], [351, 116]]}, {"minutiae": [[350, 114], [351, 111]]}, {"minutiae": [[350, 184], [350, 186]]}, {"minutiae": [[350, 208], [354, 220]]}, {"minutiae": [[350, 326], [390, 316]]}, {"minutiae": [[351, 111], [353, 109]]}, {"minutiae": [[351, 116], [353, 122]]}, {"minutiae": [[351, 116], [354, 116]]}, {"minutiae": [[351, 137], [352, 142]]}, {"minutiae": [[351, 137], [354, 132]]}, {"minutiae": [[351, 155], [362, 126]]}, {"minutiae": [[351, 155], [352, 157]]}, {"minutiae": [[351, 336], [355, 335]]}, {"minutiae": [[352, 157], [352, 167]]}, {"minutiae": [[352, 226], [354, 220]]}, {"minutiae": [[352, 232], [353, 232]]}, {"minutiae": [[353, 109], [356, 103]]}, {"minutiae": [[353, 109], [356, 110]]}, {"minutiae": [[354, 204], [357, 201]]}, {"minutiae": [[354, 220], [358, 240]]}, {"minutiae": [[354, 246], [356, 242]]}, {"minutiae": [[354, 246], [357, 257]]}, {"minutiae": [[354, 246], [356, 246]]}, {"minutiae": [[354, 272], [355, 278]]}, {"minutiae": [[354, 272], [356, 267]]}, {"minutiae": [[354, 307], [358, 307]]}, {"minutiae": [[354, 307], [358, 307]]}, {"minutiae": [[355, 195], [357, 201]]}, {"minutiae": [[355, 261], [357, 257]]}, {"minutiae": [[355, 261], [356, 263]]}, {"minutiae": [[355, 278], [359, 258]]}, {"minutiae": [[355, 335], [410, 307]]}, {"minutiae": [[355, 335], [410, 319]]}, {"minutiae": [[356, 124], [356, 125]]}, {"minutiae": [[356, 291], [358, 289]]}, {"minutiae": [[356, 291], [359, 290]]}, {"minutiae": [[356, 296], [356, 299]]}, {"minutiae": [[356, 299], [358, 298]]}, {"minutiae": [[357, 169], [358, 184]]}, {"minutiae": [[357, 201], [359, 203]]}, {"minutiae": [[357, 257], [359, 258]]}, {"minutiae": [[357, 381], [362, 367]]}, {"minutiae": [[358, 184], [359, 185]]}, {"minutiae": [[358, 184], [359, 183]]}, {"minutiae": [[358, 289], [359, 290]]}, {"minutiae": [[358, 289], [359, 285]]}, {"minutiae": [[358, 297], [358, 298]]}, {"minutiae": [[358, 298], [364, 298]]}, {"minutiae": [[358, 307], [364, 302]]}, {"minutiae": [[359, 80], [359, 83]]}, {"minutiae": [[359, 83], [359, 85]]}, {"minutiae": [[359, 83], [364, 79]]}, {"minutiae": [[359, 85], [360, 87]]}, {"minutiae": [[359, 183], [360, 184]]}, {"minutiae": [[359, 183], [362, 175]]}, {"minutiae": [[359, 185], [360, 184]]}, {"minutiae": [[359, 185], [360, 192]]}, {"minutiae": [[359, 203], [360, 192]]}, {"minutiae": [[359, 203], [374, 242]]}, {"minutiae": [[359, 258], [362, 248]]}, {"minutiae": [[359, 285], [364, 279]]}, {"minutiae": [[359, 285], [363, 287]]}, {"minutiae": [[359, 290], [363, 287]]}, {"minutiae": [[360, 90], [361, 94]]}, {"minutiae": [[360, 108], [371, 99]]}, {"minutiae": [[360, 116], [362, 114]]}, {"minutiae": [[360, 116], [362, 126]]}, {"minutiae": [[360, 116], [362, 116]]}, {"minutiae": [[360, 184], [362, 187]]}, {"minutiae": [[360, 192], [361, 192]]}, {"minutiae": [[361, 94], [370, 86]]}, {"minutiae": [[361, 168], [362, 164]]}, {"minutiae": [[361, 248], [362, 248]]}, {"minutiae": [[362, 126], [365, 124]]}, {"minutiae": [[362, 144], [363, 147]]}, {"minutiae": [[362, 164], [363, 147]]}, {"minutiae": [[362, 164], [366, 162]]}, {"minutiae": [[362, 248], [365, 247]]}, {"minutiae": [[362, 367], [369, 366]]}, {"minutiae": [[363, 147], [368, 129]]}, {"minutiae": [[363, 287], [373, 277]]}, {"minutiae": [[364, 118], [367, 118]]}, {"minutiae": [[364, 240], [365, 247]]}, {"minutiae": [[364, 298], [367, 295]]}, {"minutiae": [[364, 298], [364, 302]]}, {"minutiae": [[364, 302], [368, 302]]}, {"minutiae": [[364, 378], [366, 374]]}, {"minutiae": [[365, 114], [367, 114]]}, {"minutiae": [[365, 124], [366, 127]]}, {"minutiae": [[365, 124], [368, 119]]}, {"minutiae": [[365, 247], [366, 252]]}, {"minutiae": [[366, 162], [369, 157]]}, {"minutiae": [[366, 162], [371, 177]]}, {"minutiae": [[366, 195], [366, 193]]}, {"minutiae": [[366, 195], [380, 217]]}, {"minutiae": [[366, 195], [366, 193]]}, {"minutiae": [[367, 114], [367, 118]]}, {"minutiae": [[367, 114], [371, 99]]}, {"minutiae": [[367, 118], [368, 119]]}, {"minutiae": [[367, 294], [367, 295]]}, {"minutiae": [[367, 295], [406, 260]]}, {"minutiae": [[367, 355], [370, 352]]}, {"minutiae": [[367, 355], [381, 362]]}, {"minutiae": [[368, 119], [370, 118]]}, {"minutiae": [[368, 190], [371, 177]]}, {"minutiae": [[368, 263], [373, 255]]}, {"minutiae": [[369, 81], [369, 85]]}, {"minutiae": [[369, 81], [377, 69]]}, {"minutiae": [[369, 81], [369, 85]]}, {"minutiae": [[369, 85], [370, 86]]}, {"minutiae": [[369, 149], [370, 155]]}, {"minutiae": [[369, 157], [370, 155]]}, {"minutiae": [[369, 157], [371, 156]]}, {"minutiae": [[369, 366], [372, 378]]}, {"minutiae": [[369, 366], [374, 366]]}, {"minutiae": [[370, 86], [377, 83]]}, {"minutiae": [[370, 155], [371, 156]]}, {"minutiae": [[371, 99], [386, 88]]}, {"minutiae": [[371, 136], [386, 123]]}, {"minutiae": [[371, 156], [381, 170]]}, {"minutiae": [[371, 177], [372, 180]]}, {"minutiae": [[371, 270], [374, 267]]}, {"minutiae": [[372, 194], [378, 203]]}, {"minutiae": [[373, 255], [374, 242]]}, {"minutiae": [[373, 255], [376, 254]]}, {"minutiae": [[373, 277], [377, 271]]}, {"minutiae": [[373, 277], [394, 264]]}, {"minutiae": [[374, 142], [392, 127]]}, {"minutiae": [[374, 242], [376, 242]]}, {"minutiae": [[374, 347], [395, 344]]}, {"minutiae": [[374, 347], [380, 352]]}, {"minutiae": [[374, 366], [374, 368]]}, {"minutiae": [[374, 366], [377, 376]]}, {"minutiae": [[375, 299], [390, 286]]}, {"minutiae": [[376, 121], [388, 95]]}, {"minutiae": [[377, 83], [384, 69]]}, {"minutiae": [[377, 83], [378, 85]]}, {"minutiae": [[377, 145], [384, 158]]}, {"minutiae": [[377, 271], [388, 253]]}, {"minutiae": [[377, 271], [378, 273]]}, {"minutiae": [[378, 195], [380, 182]]}, {"minutiae": [[378, 203], [380, 217]]}, {"minutiae": [[378, 203], [385, 206]]}, {"minutiae": [[379, 104], [380, 101]]}, {"minutiae": [[380, 182], [381, 170]]}, {"minutiae": [[380, 182], [384, 193]]}, {"minutiae": [[380, 217], [382, 229]]}, {"minutiae": [[381, 170], [383, 169]]}, {"minutiae": [[381, 196], [382, 195]]}, {"minutiae": [[382, 229], [382, 241]]}, {"minutiae": [[382, 229], [384, 232]]}, {"minutiae": [[382, 246], [382, 250]]}, {"minutiae": [[382, 354], [384, 357]]}, {"minutiae": [[383, 169], [384, 170]]}, {"minutiae": [[383, 169], [384, 158]]}, {"minutiae": [[383, 340], [388, 337]]}, {"minutiae": [[384, 79], [387, 76]]}, {"minutiae": [[384, 158], [389, 167]]}, {"minutiae": [[384, 170], [385, 170]]}, {"minutiae": [[384, 170], [387, 178]]}, {"minutiae": [[385, 206], [386, 201]]}, {"minutiae": [[385, 206], [390, 248]]}, {"minutiae": [[386, 88], [387, 88]]}, {"minutiae": [[386, 88], [396, 75]]}, {"minutiae": [[386, 123], [405, 104]]}, {"minutiae": [[386, 123], [387, 125]]}, {"minutiae": [[386, 376], [389, 369]]}, {"minutiae": [[387, 76], [392, 71]]}, {"minutiae": [[387, 76], [388, 78]]}, {"minutiae": [[387, 197], [389, 194]]}, {"minutiae": [[388, 150], [390, 141]]}, {"minutiae": [[388, 253], [390, 248]]}, {"minutiae": [[388, 253], [391, 253]]}, {"minutiae": [[388, 304], [413, 282]]}, {"minutiae": [[388, 360], [399, 350]]}, {"minutiae": [[389, 191], [389, 194]]}, {"minutiae": [[389, 194], [399, 207]]}, {"minutiae": [[389, 369], [390, 366]]}, {"minutiae": [[389, 369], [390, 371]]}, {"minutiae": [[390, 108], [391, 105]]}, {"minutiae": [[390, 108], [390, 113]]}, {"minutiae": [[390, 108], [393, 107]]}, {"minutiae": [[390, 138], [390, 141]]}, {"minutiae": [[390, 141], [395, 139]]}, {"minutiae": [[390, 178], [393, 180]]}, {"minutiae": [[390, 248], [391, 249]]}, {"minutiae": [[390, 339], [396, 335]]}, {"minutiae": [[390, 366], [391, 366]]}, {"minutiae": [[390, 366], [396, 354]]}, {"minutiae": [[391, 105], [400, 74]]}, {"minutiae": [[391, 105], [393, 107]]}, {"minutiae": [[391, 249], [391, 253]]}, {"minutiae": [[391, 249], [400, 215]]}, {"minutiae": [[391, 253], [394, 264]]}, {"minutiae": [[393, 107], [398, 98]]}, {"minutiae": [[393, 180], [394, 190]]}, {"minutiae": [[393, 180], [396, 147]]}, {"minutiae": [[394, 264], [399, 261]]}, {"minutiae": [[394, 373], [394, 374]]}, {"minutiae": [[395, 139], [398, 132]]}, {"minutiae": [[395, 139], [396, 141]]}, {"minutiae": [[395, 344], [396, 346]]}, {"minutiae": [[395, 344], [404, 340]]}, {"minutiae": [[396, 72], [396, 75]]}, {"minutiae": [[396, 75], [397, 75]]}, {"minutiae": [[396, 372], [399, 365]]}, {"minutiae": [[397, 75], [397, 76]]}, {"minutiae": [[397, 75], [400, 74]]}, {"minutiae": [[397, 363], [399, 350]]}, {"minutiae": [[398, 132], [402, 121]]}, {"minutiae": [[398, 132], [402, 132]]}, {"minutiae": [[398, 210], [398, 212]]}, {"minutiae": [[398, 210], [398, 212]]}, {"minutiae": [[398, 210], [399, 207]]}, {"minutiae": [[398, 212], [400, 215]]}, {"minutiae": [[399, 207], [403, 187]]}, {"minutiae": [[399, 252], [401, 249]]}, {"minutiae": [[399, 261], [405, 253]]}, {"minutiae": [[399, 261], [400, 263]]}, {"minutiae": [[399, 350], [405, 341]]}, {"minutiae": [[400, 74], [403, 69]]}, {"minutiae": [[400, 215], [402, 216]]}, {"minutiae": [[400, 336], [412, 324]]}, {"minutiae": [[401, 249], [404, 236]]}, {"minutiae": [[401, 249], [405, 253]]}, {"minutiae": [[401, 277], [410, 267]]}, {"minutiae": [[401, 277], [402, 279]]}, {"minutiae": [[402, 132], [404, 128]]}, {"minutiae": [[402, 132], [404, 150]]}, {"minutiae": [[402, 308], [404, 306]]}, {"minutiae": [[402, 366], [412, 352]]}, {"minutiae": [[403, 187], [404, 150]]}, {"minutiae": [[403, 187], [407, 225]]}, {"minutiae": [[404, 128], [405, 128]]}, {"minutiae": [[404, 128], [409, 123]]}, {"minutiae": [[404, 150], [408, 144]]}, {"minutiae": [[404, 285], [405, 285]]}, {"minutiae": [[404, 340], [405, 341]]}, {"minutiae": [[404, 340], [405, 339]]}, {"minutiae": [[405, 84], [418, 62]]}, {"minutiae": [[405, 104], [416, 82]]}, {"minutiae": [[405, 104], [448, 60]]}, {"minutiae": [[405, 253], [411, 250]]}, {"minutiae": [[405, 253], [406, 255]]}, {"minutiae": [[405, 339], [406, 340]]}, {"minutiae": [[405, 339], [408, 335]]}, {"minutiae": [[405, 341], [406, 340]]}, {"minutiae": [[406, 228], [407, 225]]}, {"minutiae": [[406, 282], [412, 279]]}, {"minutiae": [[406, 340], [419, 331]]}, {"minutiae": [[407, 225], [412, 232]]}, {"minutiae": [[407, 348], [408, 348]]}, {"minutiae": [[408, 144], [409, 144]]}, {"minutiae": [[408, 144], [411, 139]]}, {"minutiae": [[408, 302], [410, 305]]}, {"minutiae": [[409, 123], [421, 105]]}, {"minutiae": [[409, 123], [412, 128]]}, {"minutiae": [[410, 150], [410, 153]]}, {"minutiae": [[410, 267], [411, 265]]}, {"minutiae": [[410, 267], [413, 269]]}, {"minutiae": [[410, 297], [416, 289]]}, {"minutiae": [[410, 297], [410, 305]]}, {"minutiae": [[410, 305], [410, 307]]}, {"minutiae": [[410, 307], [412, 309]]}, {"minutiae": [[410, 319], [424, 300]]}, {"minutiae": [[410, 319], [412, 324]]}, {"minutiae": [[411, 139], [412, 132]]}, {"minutiae": [[411, 139], [417, 149]]}, {"minutiae": [[411, 188], [414, 191]]}, {"minutiae": [[411, 250], [412, 239]]}, {"minutiae": [[411, 250], [412, 257]]}, {"minutiae": [[411, 265], [412, 257]]}, {"minutiae": [[411, 265], [413, 264]]}, {"minutiae": [[412, 128], [412, 132]]}, {"minutiae": [[412, 128], [414, 128]]}, {"minutiae": [[412, 132], [414, 132]]}, {"minutiae": [[412, 197], [415, 193]]}, {"minutiae": [[412, 232], [412, 239]]}, {"minutiae": [[412, 232], [412, 239]]}, {"minutiae": [[412, 257], [413, 264]]}, {"minutiae": [[412, 279], [413, 269]]}, {"minutiae": [[412, 279], [413, 282]]}, {"minutiae": [[412, 324], [421, 315]]}, {"minutiae": [[412, 352], [413, 352]]}, {"minutiae": [[412, 352], [428, 326]]}, {"minutiae": [[413, 264], [413, 269]]}, {"minutiae": [[413, 282], [416, 289]]}, {"minutiae": [[414, 166], [417, 166]]}, {"minutiae": [[414, 175], [416, 184]]}, {"minutiae": [[414, 191], [415, 193]]}, {"minutiae": [[414, 191], [416, 184]]}, {"minutiae": [[414, 361], [424, 345]]}, {"minutiae": [[415, 193], [418, 205]]}, {"minutiae": [[416, 82], [440, 52]]}, {"minutiae": [[416, 82], [424, 76]]}, {"minutiae": [[416, 173], [417, 171]]}, {"minutiae": [[416, 184], [418, 184]]}, {"minutiae": [[416, 224], [418, 207]]}, {"minutiae": [[416, 289], [419, 289]]}, {"minutiae": [[417, 149], [417, 166]]}, {"minutiae": [[417, 149], [421, 147]]}, {"minutiae": [[417, 166], [417, 171]]}, {"minutiae": [[417, 171], [420, 178]]}, {"minutiae": [[418, 205], [418, 207]]}, {"minutiae": [[418, 205], [420, 204]]}, {"minutiae": [[418, 207], [420, 208]]}, {"minutiae": [[419, 289], [426, 269]]}, {"minutiae": [[419, 289], [420, 295]]}, {"minutiae": [[419, 331], [426, 322]]}, {"minutiae": [[419, 331], [420, 333]]}, {"minutiae": [[420, 260], [423, 236]]}, {"minutiae": [[421, 105], [447, 76]]}, {"minutiae": [[421, 105], [422, 107]]}, {"minutiae": [[421, 132], [422, 126]]}, {"minutiae": [[421, 132], [421, 147]]}, {"minutiae": [[421, 132], [424, 131]]}, {"minutiae": [[421, 147], [422, 149]]}, {"minutiae": [[421, 315], [425, 311]]}, {"minutiae": [[421, 315], [422, 317]]}, {"minutiae": [[422, 126], [428, 108]]}, {"minutiae": [[422, 126], [426, 117]]}, {"minutiae": [[423, 236], [427, 211]]}, {"minutiae": [[423, 236], [430, 224]]}, {"minutiae": [[424, 181], [427, 211]]}, {"minutiae": [[424, 300], [428, 295]]}, {"minutiae": [[424, 300], [425, 311]]}, {"minutiae": [[424, 358], [428, 352]]}, {"minutiae": [[425, 74], [426, 74]]}, {"minutiae": [[425, 311], [426, 313]]}, {"minutiae": [[426, 269], [436, 234]]}, {"minutiae": [[426, 269], [429, 272]]}, {"minutiae": [[426, 322], [430, 318]]}, {"minutiae": [[426, 322], [428, 326]]}, {"minutiae": [[427, 78], [442, 52]]}, {"minutiae": [[427, 211], [428, 214]]}, {"minutiae": [[428, 295], [429, 296]]}, {"minutiae": [[428, 295], [429, 272]]}, {"minutiae": [[428, 326], [429, 327]]}, {"minutiae": [[429, 123], [429, 124]]}, {"minutiae": [[429, 272], [432, 270]]}, {"minutiae": [[429, 327], [430, 318]]}, {"minutiae": [[429, 327], [430, 329]]}, {"minutiae": [[430, 135], [435, 209]]}, {"minutiae": [[430, 224], [435, 209]]}, {"minutiae": [[430, 224], [437, 233]]}, {"minutiae": [[430, 318], [438, 308]]}, {"minutiae": [[432, 110], [460, 69]]}, {"minutiae": [[432, 121], [433, 119]]}, {"minutiae": [[432, 130], [435, 130]]}, {"minutiae": [[433, 119], [436, 115]]}, {"minutiae": [[433, 119], [434, 122]]}, {"minutiae": [[433, 358], [436, 350]]}, {"minutiae": [[434, 268], [438, 247]]}, {"minutiae": [[435, 130], [436, 115]]}, {"minutiae": [[435, 130], [437, 161]]}, {"minutiae": [[435, 209], [436, 211]]}, {"minutiae": [[436, 115], [442, 106]]}, {"minutiae": [[436, 234], [437, 233]]}, {"minutiae": [[436, 234], [438, 247]]}, {"minutiae": [[436, 350], [438, 327]]}, {"minutiae": [[436, 350], [441, 345]]}, {"minutiae": [[437, 161], [438, 185]]}, {"minutiae": [[437, 161], [438, 163]]}, {"minutiae": [[437, 233], [446, 199]]}, {"minutiae": [[438, 247], [440, 248]]}, {"minutiae": [[438, 264], [438, 291]]}, {"minutiae": [[438, 291], [438, 308]]}, {"minutiae": [[438, 291], [440, 290]]}, {"minutiae": [[438, 308], [440, 340]]}, {"minutiae": [[438, 340], [440, 340]]}, {"minutiae": [[440, 263], [441, 261]]}, {"minutiae": [[440, 290], [445, 281]]}, {"minutiae": [[440, 290], [442, 293]]}, {"minutiae": [[440, 340], [441, 345]]}, {"minutiae": [[441, 261], [442, 256]]}, {"minutiae": [[441, 261], [442, 264]]}, {"minutiae": [[441, 345], [446, 355]]}, {"minutiae": [[442, 154], [444, 158]]}, {"minutiae": [[442, 242], [445, 242]]}, {"minutiae": [[442, 267], [443, 271]]}, {"minutiae": [[443, 271], [445, 281]]}, {"minutiae": [[443, 271], [465, 219]]}, {"minutiae": [[444, 76], [447, 76]]}, {"minutiae": [[444, 158], [450, 137]]}, {"minutiae": [[444, 158], [446, 180]]}, {"minutiae": [[444, 249], [445, 242]]}, {"minutiae": [[445, 129], [447, 125]]}, {"minutiae": [[445, 242], [447, 239]]}, {"minutiae": [[445, 281], [454, 264]]}, {"minutiae": [[446, 180], [446, 199]]}, {"minutiae": [[446, 180], [448, 180]]}, {"minutiae": [[446, 199], [448, 200]]}, {"minutiae": [[446, 226], [447, 229]]}, {"minutiae": [[446, 251], [447, 239]]}, {"minutiae": [[446, 294], [449, 295]]}, {"minutiae": [[446, 348], [446, 355]]}, {"minutiae": [[446, 355], [447, 358]]}, {"minutiae": [[447, 76], [455, 52]]}, {"minutiae": [[447, 125], [451, 109]]}, {"minutiae": [[447, 125], [451, 128]]}, {"minutiae": [[447, 229], [448, 236]]}, {"minutiae": [[447, 229], [453, 219]]}, {"minutiae": [[447, 239], [448, 238]]}, {"minutiae": [[448, 217], [450, 214]]}, {"minutiae": [[448, 236], [448, 238]]}, {"minutiae": [[448, 236], [453, 219]]}, {"minutiae": [[448, 238], [452, 238]]}, {"minutiae": [[449, 295], [451, 303]]}, {"minutiae": [[449, 295], [451, 294]]}, {"minutiae": [[450, 137], [451, 128]]}, {"minutiae": [[450, 137], [452, 136]]}, {"minutiae": [[450, 195], [450, 198]]}, {"minutiae": [[450, 214], [451, 202]]}, {"minutiae": [[450, 214], [453, 215]]}, {"minutiae": [[450, 342], [454, 338]]}, {"minutiae": [[451, 109], [468, 63]]}, {"minutiae": [[451, 109], [457, 105]]}, {"minutiae": [[451, 128], [454, 125]]}, {"minutiae": [[451, 294], [454, 284]]}, {"minutiae": [[451, 294], [453, 296]]}, {"minutiae": [[451, 303], [453, 296]]}, {"minutiae": [[451, 303], [452, 307]]}, {"minutiae": [[452, 280], [454, 284]]}, {"minutiae": [[452, 307], [453, 329]]}, {"minutiae": [[452, 307], [454, 309]]}, {"minutiae": [[453, 196], [456, 186]]}, {"minutiae": [[453, 215], [453, 219]]}, {"minutiae": [[453, 215], [463, 192]]}, {"minutiae": [[453, 296], [458, 292]]}, {"minutiae": [[453, 329], [454, 338]]}, {"minutiae": [[453, 329], [456, 328]]}, {"minutiae": [[454, 125], [455, 115]]}, {"minutiae": [[454, 125], [456, 130]]}, {"minutiae": [[454, 168], [456, 168]]}, {"minutiae": [[454, 284], [456, 284]]}, {"minutiae": [[454, 338], [460, 358]]}, {"minutiae": [[456, 168], [460, 131]]}, {"minutiae": [[456, 168], [456, 186]]}, {"minutiae": [[456, 186], [458, 186]]}, {"minutiae": [[456, 284], [462, 274]]}, {"minutiae": [[456, 284], [458, 292]]}, {"minutiae": [[457, 105], [462, 96]]}, {"minutiae": [[457, 105], [458, 107]]}, {"minutiae": [[458, 125], [458, 126]]}, {"minutiae": [[458, 292], [460, 292]]}, {"minutiae": [[458, 317], [461, 310]]}, {"minutiae": [[460, 62], [462, 52]]}, {"minutiae": [[460, 64], [460, 69]]}, {"minutiae": [[460, 69], [461, 69]]}, {"minutiae": [[460, 261], [462, 256]]}, {"minutiae": [[461, 69], [467, 62]]}, {"minutiae": [[461, 69], [464, 70]]}, {"minutiae": [[462, 215], [467, 195]]}, {"minutiae": [[462, 256], [473, 220]]}, {"minutiae": [[462, 256], [462, 274]]}, {"minutiae": [[462, 274], [463, 275]]}, {"minutiae": [[462, 300], [465, 300]]}, {"minutiae": [[462, 324], [466, 324]]}, {"minutiae": [[463, 192], [464, 191]]}, {"minutiae": [[463, 192], [467, 195]]}, {"minutiae": [[463, 275], [463, 283]]}, {"minutiae": [[463, 275], [471, 265]]}, {"minutiae": [[464, 158], [466, 158]]}, {"minutiae": [[464, 165], [466, 163]]}, {"minutiae": [[464, 191], [466, 185]]}, {"minutiae": [[464, 191], [466, 190]]}, {"minutiae": [[464, 303], [465, 300]]}, {"minutiae": [[464, 347], [467, 343]]}, {"minutiae": [[465, 300], [466, 299]]}, {"minutiae": [[466, 158], [485, 84]]}, {"minutiae": [[466, 158], [466, 163]]}, {"minutiae": [[466, 163], [466, 185]]}, {"minutiae": [[466, 185], [467, 195]]}, {"minutiae": [[466, 299], [471, 277]]}, {"minutiae": [[466, 299], [467, 323]]}, {"minutiae": [[466, 324], [467, 325]]}, {"minutiae": [[466, 324], [467, 323]]}, {"minutiae": [[467, 62], [468, 63]]}, {"minutiae": [[467, 62], [468, 57]]}, {"minutiae": [[467, 93], [480, 69]]}, {"minutiae": [[467, 323], [468, 324]]}, {"minutiae": [[467, 325], [468, 324]]}, {"minutiae": [[467, 325], [467, 343]]}, {"minutiae": [[467, 343], [471, 351]]}, {"minutiae": [[468, 63], [471, 61]]}, {"minutiae": [[468, 214], [470, 214]]}, {"minutiae": [[468, 324], [472, 328]]}, {"minutiae": [[468, 358], [471, 351]]}, {"minutiae": [[470, 214], [478, 180]]}, {"minutiae": [[470, 214], [473, 220]]}, {"minutiae": [[471, 61], [471, 62]]}, {"minutiae": [[471, 61], [475, 52]]}, {"minutiae": [[471, 265], [483, 207]]}, {"minutiae": [[471, 265], [472, 267]]}, {"minutiae": [[471, 351], [472, 353]]}, {"minutiae": [[472, 78], [477, 65]]}, {"minutiae": [[472, 337], [472, 338]]}, {"minutiae": [[473, 220], [477, 215]]}, {"minutiae": [[475, 273], [476, 266]]}, {"minutiae": [[476, 113], [480, 111]]}, {"minutiae": [[476, 302], [477, 299]]}, {"minutiae": [[476, 358], [478, 357]]}, {"minutiae": [[477, 65], [479, 63]]}, {"minutiae": [[477, 65], [478, 67]]}, {"minutiae": [[477, 215], [479, 211]]}, {"minutiae": [[477, 215], [478, 217]]}, {"minutiae": [[477, 299], [495, 211]]}, {"minutiae": [[477, 299], [479, 302]]}, {"minutiae": [[478, 180], [480, 111]]}, {"minutiae": [[478, 180], [480, 171]]}, {"minutiae": [[478, 208], [479, 211]]}, {"minutiae": [[478, 357], [479, 356]]}, {"minutiae": [[478, 357], [480, 358]]}, {"minutiae": [[479, 63], [485, 54]]}, {"minutiae": [[479, 63], [480, 65]]}, {"minutiae": [[479, 211], [483, 207]]}, {"minutiae": [[479, 302], [480, 299]]}, {"minutiae": [[479, 302], [482, 338]]}, {"minutiae": [[479, 356], [482, 338]]}, {"minutiae": [[479, 356], [482, 356]]}, {"minutiae": [[480, 111], [481, 110]]}, {"minutiae": [[481, 110], [486, 98]]}, {"minutiae": [[481, 110], [485, 107]]}, {"minutiae": [[482, 338], [487, 358]]}, {"minutiae": [[483, 207], [497, 99]]}, {"minutiae": [[484, 73], [487, 69]]}, {"minutiae": [[485, 51], [485, 54]]}, {"minutiae": [[485, 54], [487, 69]]}, {"minutiae": [[485, 84], [489, 75]]}, {"minutiae": [[485, 84], [487, 97]]}, {"minutiae": [[485, 107], [486, 98]]}, {"minutiae": [[485, 107], [486, 109]]}, {"minutiae": [[486, 98], [487, 97]]}, {"minutiae": [[486, 309], [492, 270]]}, {"minutiae": [[487, 69], [489, 69]]}, {"minutiae": [[487, 97], [503, 63]]}, {"minutiae": [[489, 69], [489, 75]]}, {"minutiae": [[489, 69], [494, 59]]}, {"minutiae": [[489, 75], [492, 74]]}, {"minutiae": [[490, 210], [493, 195]]}, {"minutiae": [[492, 258], [492, 268]]}, {"minutiae": [[492, 268], [492, 270]]}, {"minutiae": [[492, 268], [498, 263]]}, {"minutiae": [[492, 270], [494, 275]]}, {"minutiae": [[492, 312], [493, 319]]}, {"minutiae": [[493, 319], [497, 344]]}, {"minutiae": [[493, 319], [494, 313]]}, {"minutiae": [[494, 51], [494, 59]]}, {"minutiae": [[494, 59], [496, 61]]}, {"minutiae": [[494, 208], [495, 211]]}, {"minutiae": [[495, 211], [501, 198]]}, {"minutiae": [[496, 148], [498, 152]]}, {"minutiae": [[496, 326], [498, 326]]}, {"minutiae": [[497, 99], [498, 95]]}, {"minutiae": [[497, 99], [498, 95]]}, {"minutiae": [[497, 344], [499, 358]]}, {"minutiae": [[497, 344], [499, 343]]}, {"minutiae": [[498, 53], [499, 51]]}, {"minutiae": [[498, 95], [508, 68]]}, {"minutiae": [[498, 152], [513, 84]]}, {"minutiae": [[498, 152], [499, 155]]}, {"minutiae": [[498, 192], [499, 155]]}, {"minutiae": [[498, 263], [504, 233]]}, {"minutiae": [[498, 263], [500, 296]]}, {"minutiae": [[498, 326], [500, 296]]}, {"minutiae": [[498, 326], [499, 343]]}, {"minutiae": [[499, 155], [500, 157]]}, {"minutiae": [[499, 343], [500, 345]]}, {"minutiae": [[500, 222], [503, 222]]}, {"minutiae": [[500, 227], [502, 225]]}, {"minutiae": [[500, 296], [511, 334]]}, {"minutiae": [[501, 198], [507, 188]]}, {"minutiae": [[501, 198], [504, 210]]}, {"minutiae": [[502, 225], [503, 222]]}, {"minutiae": [[502, 225], [504, 233]]}, {"minutiae": [[503, 63], [511, 45]]}, {"minutiae": [[503, 63], [508, 68]]}, {"minutiae": [[503, 222], [504, 210]]}, {"minutiae": [[504, 210], [506, 210]]}, {"minutiae": [[504, 233], [507, 235]]}, {"minutiae": [[504, 253], [504, 254]]}, {"minutiae": [[505, 358], [509, 347]]}, {"minutiae": [[506, 243], [509, 240]]}, {"minutiae": [[506, 276], [509, 240]]}, {"minutiae": [[507, 188], [510, 182]]}, {"minutiae": [[507, 188], [511, 193]]}, {"minutiae": [[507, 235], [509, 229]]}, {"minutiae": [[507, 235], [509, 240]]}, {"minutiae": [[508, 68], [511, 62]]}, {"minutiae": [[508, 143], [510, 141]]}, {"minutiae": [[508, 159], [511, 155]]}, {"minutiae": [[508, 159], [508, 163]]}, {"minutiae": [[508, 159], [511, 160]]}, {"minutiae": [[508, 163], [509, 165]]}, {"minutiae": [[508, 163], [511, 160]]}, {"minutiae": [[508, 296], [510, 296]]}, {"minutiae": [[509, 165], [510, 182]]}, {"minutiae": [[509, 165], [512, 164]]}, {"minutiae": [[509, 347], [511, 334]]}, {"minutiae": [[509, 347], [511, 358]]}, {"minutiae": [[510, 84], [513, 84]]}, {"minutiae": [[510, 141], [514, 121]]}, {"minutiae": [[510, 141], [511, 155]]}, {"minutiae": [[510, 182], [514, 191]]}, {"minutiae": [[510, 296], [516, 284]]}, {"minutiae": [[510, 296], [511, 301]]}, {"minutiae": [[511, 62], [512, 58]]}, {"minutiae": [[511, 62], [512, 64]]}, {"minutiae": [[511, 155], [511, 160]]}, {"minutiae": [[511, 193], [511, 197]]}, {"minutiae": [[511, 193], [514, 191]]}, {"minutiae": [[511, 193], [511, 197]]}, {"minutiae": [[511, 197], [516, 225]]}, {"minutiae": [[511, 301], [512, 303]]}, {"minutiae": [[511, 301], [512, 303]]}, {"minutiae": [[511, 334], [521, 300]]}, {"minutiae": [[513, 84], [521, 69]]}, {"minutiae": [[514, 121], [516, 109]]}, {"minutiae": [[514, 121], [516, 120]]}, {"minutiae": [[514, 191], [516, 192]]}, {"minutiae": [[516, 62], [522, 48]]}, {"minutiae": [[516, 109], [535, 51]]}, {"minutiae": [[516, 109], [518, 111]]}, {"minutiae": [[516, 192], [519, 187]]}, {"minutiae": [[516, 192], [516, 198]]}, {"minutiae": [[516, 225], [516, 237]]}, {"minutiae": [[516, 225], [523, 209]]}, {"minutiae": [[516, 284], [521, 263]]}, {"minutiae": [[516, 284], [518, 291]]}, {"minutiae": [[519, 187], [523, 177]]}, {"minutiae": [[519, 187], [520, 189]]}, {"minutiae": [[519, 358], [520, 353]]}, {"minutiae": [[520, 128], [522, 132]]}, {"minutiae": [[520, 174], [522, 174]]}, {"minutiae": [[520, 353], [532, 321]]}, {"minutiae": [[520, 353], [522, 352]]}, {"minutiae": [[521, 69], [529, 51]]}, {"minutiae": [[521, 69], [522, 71]]}, {"minutiae": [[521, 263], [523, 254]]}, {"minutiae": [[521, 263], [526, 272]]}, {"minutiae": [[521, 300], [524, 292]]}, {"minutiae": [[521, 300], [524, 308]]}, {"minutiae": [[522, 118], [525, 118]]}, {"minutiae": [[522, 132], [525, 118]]}, {"minutiae": [[522, 132], [523, 138]]}, {"minutiae": [[522, 174], [523, 138]]}, {"minutiae": [[522, 174], [523, 177]]}, {"minutiae": [[523, 138], [526, 138]]}, {"minutiae": [[523, 177], [524, 179]]}, {"minutiae": [[523, 200], [523, 209]]}, {"minutiae": [[523, 200], [529, 189]]}, {"minutiae": [[523, 200], [525, 202]]}, {"minutiae": [[523, 209], [525, 202]]}, {"minutiae": [[523, 209], [524, 214]]}, {"minutiae": [[523, 254], [529, 243]]}, {"minutiae": [[523, 254], [526, 254]]}, {"minutiae": [[524, 292], [526, 278]]}, {"minutiae": [[524, 292], [528, 300]]}, {"minutiae": [[525, 118], [545, 57]]}, {"minutiae": [[525, 202], [528, 202]]}, {"minutiae": [[526, 272], [526, 278]]}, {"minutiae": [[526, 272], [530, 268]]}, {"minutiae": [[526, 278], [528, 282]]}, {"minutiae": [[529, 171], [531, 177]]}, {"minutiae": [[529, 189], [531, 177]]}, {"minutiae": [[529, 189], [530, 198]]}, {"minutiae": [[529, 243], [534, 202]]}, {"minutiae": [[529, 243], [531, 267]]}, {"minutiae": [[530, 147], [536, 119]]}, {"minutiae": [[530, 268], [531, 267]]}, {"minutiae": [[530, 268], [532, 270]]}, {"minutiae": [[531, 177], [535, 168]]}, {"minutiae": [[531, 267], [534, 268]]}, {"minutiae": [[532, 168], [535, 168]]}, {"minutiae": [[532, 270], [533, 270]]}, {"minutiae": [[532, 270], [532, 273]]}, {"minutiae": [[532, 281], [532, 288]]}, {"minutiae": [[532, 321], [536, 303]]}, {"minutiae": [[532, 321], [537, 337]]}, {"minutiae": [[534, 114], [536, 119]]}, {"minutiae": [[535, 168], [539, 138]]}, {"minutiae": [[535, 364], [536, 352]]}, {"minutiae": [[536, 119], [537, 118]]}, {"minutiae": [[536, 303], [538, 297]]}, {"minutiae": [[536, 303], [538, 304]]}, {"minutiae": [[536, 351], [536, 352]]}, {"minutiae": [[536, 351], [537, 337]]}, {"minutiae": [[536, 351], [540, 350]]}, {"minutiae": [[536, 352], [542, 358]]}, {"minutiae": [[537, 118], [544, 100]]}, {"minutiae": [[537, 118], [539, 138]]}, {"minutiae": [[537, 337], [542, 325]]}, {"minutiae": [[538, 297], [540, 289]]}, {"minutiae": [[538, 297], [540, 299]]}, {"minutiae": [[539, 138], [543, 164]]}, {"minutiae": [[540, 54], [541, 54]]}, {"minutiae": [[540, 164], [543, 164]]}, {"minutiae": [[540, 289], [542, 286]]}, {"minutiae": [[540, 289], [548, 291]]}, {"minutiae": [[541, 171], [542, 175]]}, {"minutiae": [[541, 220], [547, 264]]}, {"minutiae": [[542, 175], [542, 188]]}, {"minutiae": [[542, 175], [543, 164]]}, {"minutiae": [[542, 286], [545, 273]]}, {"minutiae": [[542, 286], [548, 288]]}, {"minutiae": [[542, 358], [542, 365]]}, {"minutiae": [[542, 358], [544, 347]]}, {"minutiae": [[544, 100], [553, 65]]}, {"minutiae": [[544, 100], [548, 102]]}, {"minutiae": [[544, 294], [548, 294]]}, {"minutiae": [[544, 302], [547, 303]]}, {"minutiae": [[545, 273], [547, 264]]}, {"minutiae": [[545, 273], [548, 288]]}, {"minutiae": [[546, 223], [549, 217]]}, {"minutiae": [[547, 264], [554, 277]]}, {"minutiae": [[547, 303], [548, 302]]}, {"minutiae": [[547, 303], [549, 319]]}, {"minutiae": [[548, 288], [548, 291]]}, {"minutiae": [[548, 291], [548, 294]]}, {"minutiae": [[548, 294], [548, 302]]}, {"minutiae": [[548, 302], [549, 319]]}, {"minutiae": [[548, 343], [549, 319]]}, {"minutiae": [[549, 217], [553, 206]]}, {"minutiae": [[549, 217], [554, 221]]}, {"minutiae": [[550, 149], [554, 96]]}, {"minutiae": [[550, 149], [550, 152]]}, {"minutiae": [[550, 149], [552, 151]]}, {"minutiae": [[551, 366], [556, 356]]}, {"minutiae": [[552, 176], [554, 179]]}, {"minutiae": [[552, 224], [554, 223]]}, {"minutiae": [[553, 206], [554, 198]]}, {"minutiae": [[553, 206], [557, 209]]}, {"minutiae": [[554, 168], [557, 168]]}, {"minutiae": [[554, 179], [554, 198]]}, {"minutiae": [[554, 179], [560, 174]]}, {"minutiae": [[554, 198], [555, 199]]}, {"minutiae": [[554, 221], [554, 223]]}, {"minutiae": [[554, 221], [557, 209]]}, {"minutiae": [[554, 223], [556, 242]]}, {"minutiae": [[555, 199], [559, 198]]}, {"minutiae": [[555, 199], [556, 201]]}, {"minutiae": [[556, 242], [556, 258]]}, {"minutiae": [[556, 242], [558, 245]]}, {"minutiae": [[556, 356], [563, 327]]}, {"minutiae": [[556, 356], [558, 366]]}, {"minutiae": [[557, 168], [564, 162]]}, {"minutiae": [[557, 168], [560, 174]]}, {"minutiae": [[557, 209], [559, 198]]}, {"minutiae": [[558, 116], [563, 82]]}, {"minutiae": [[558, 295], [558, 298]]}, {"minutiae": [[559, 198], [561, 174]]}, {"minutiae": [[560, 75], [563, 82]]}, {"minutiae": [[560, 174], [561, 174]]}, {"minutiae": [[561, 158], [564, 160]]}, {"minutiae": [[561, 174], [564, 172]]}, {"minutiae": [[562, 264], [566, 288]]}, {"minutiae": [[563, 82], [566, 80]]}, {"minutiae": [[563, 327], [566, 312]]}, {"minutiae": [[563, 327], [565, 335]]}, {"minutiae": [[564, 160], [571, 135]]}, {"minutiae": [[564, 160], [564, 162]]}, {"minutiae": [[564, 162], [564, 172]]}, {"minutiae": [[564, 172], [568, 180]]}, {"minutiae": [[564, 338], [565, 335]]}, {"minutiae": [[565, 335], [566, 351]]}, {"minutiae": [[566, 80], [571, 65]]}, {"minutiae": [[566, 80], [568, 83]]}, {"minutiae": [[566, 288], [566, 312]]}, {"minutiae": [[566, 288], [568, 287]]}, {"minutiae": [[566, 312], [570, 312]]}, {"minutiae": [[566, 354], [566, 366]]}, {"minutiae": [[568, 130], [571, 135]]}, {"minutiae": [[568, 287], [570, 271]]}, {"minutiae": [[568, 287], [570, 291]]}, {"minutiae": [[570, 271], [571, 247]]}, {"minutiae": [[570, 271], [571, 247]]}, {"minutiae": [[570, 346], [571, 343]]}, {"minutiae": [[571, 135], [575, 103]]}, {"minutiae": [[571, 247], [578, 205]]}, {"minutiae": [[571, 343], [573, 334]]}, {"minutiae": [[571, 343], [572, 347]]}, {"minutiae": [[573, 313], [575, 315]]}, {"minutiae": [[573, 325], [573, 334]]}, {"minutiae": [[573, 325], [575, 315]]}, {"minutiae": [[573, 325], [573, 334]]}, {"minutiae": [[574, 198], [578, 204]]}, {"minutiae": [[574, 350], [577, 355]]}, {"minutiae": [[575, 103], [577, 94]]}, {"minutiae": [[575, 103], [577, 101]]}, {"minutiae": [[575, 315], [577, 315]]}, {"minutiae": [[576, 278], [578, 275]]}, {"minutiae": [[577, 94], [583, 71]]}, {"minutiae": [[577, 94], [577, 101]]}, {"minutiae": [[577, 101], [583, 190]]}, {"minutiae": [[577, 305], [579, 294]]}, {"minutiae": [[577, 305], [578, 310]]}, {"minutiae": [[577, 305], [580, 295]]}, {"minutiae": [[577, 315], [578, 310]]}, {"minutiae": [[577, 315], [583, 327]]}, {"minutiae": [[577, 355], [578, 354]]}, {"minutiae": [[577, 355], [578, 362]]}, {"minutiae": [[577, 366], [578, 362]]}, {"minutiae": [[578, 204], [578, 205]]}, {"minutiae": [[578, 204], [585, 197]]}, {"minutiae": [[578, 205], [582, 213]]}, {"minutiae": [[578, 275], [578, 278]]}, {"minutiae": [[578, 275], [583, 257]]}, {"minutiae": [[578, 310], [580, 310]]}, {"minutiae": [[578, 354], [582, 350]]}, {"minutiae": [[578, 354], [580, 357]]}, {"minutiae": [[578, 362], [581, 361]]}, {"minutiae": [[579, 285], [580, 293]]}, {"minutiae": [[579, 294], [580, 295]]}, {"minutiae": [[579, 294], [580, 293]]}, {"minutiae": [[580, 293], [581, 294]]}, {"minutiae": [[580, 295], [581, 294]]}, {"minutiae": [[580, 338], [582, 337]]}, {"minutiae": [[581, 294], [591, 272]]}, {"minutiae": [[581, 361], [582, 350]]}, {"minutiae": [[581, 361], [582, 363]]}, {"minutiae": [[582, 219], [584, 234]]}, {"minutiae": [[582, 242], [583, 245]]}, {"minutiae": [[582, 337], [583, 337]]}, {"minutiae": [[582, 337], [583, 331]]}, {"minutiae": [[582, 340], [584, 344]]}, {"minutiae": [[582, 350], [584, 344]]}, {"minutiae": [[583, 71], [584, 69]]}, {"minutiae": [[583, 71], [595, 127]]}, {"minutiae": [[583, 190], [589, 163]]}, {"minutiae": [[583, 190], [585, 197]]}, {"minutiae": [[583, 245], [583, 257]]}, {"minutiae": [[583, 245], [585, 244]]}, {"minutiae": [[583, 257], [587, 253]]}, {"minutiae": [[583, 327], [583, 331]]}, {"minutiae": [[583, 327], [588, 313]]}, {"minutiae": [[583, 331], [585, 334]]}, {"minutiae": [[583, 337], [585, 334]]}, {"minutiae": [[583, 337], [587, 338]]}, {"minutiae": [[584, 344], [587, 338]]}, {"minutiae": [[585, 197], [585, 244]]}, {"minutiae": [[585, 244], [589, 248]]}, {"minutiae": [[585, 334], [587, 334]]}, {"minutiae": [[587, 253], [589, 248]]}, {"minutiae": [[587, 253], [588, 255]]}, {"minutiae": [[587, 334], [587, 338]]}, {"minutiae": [[587, 334], [588, 313]]}, {"minutiae": [[588, 313], [592, 307]]}, {"minutiae": [[589, 151], [589, 163]]}, {"minutiae": [[589, 151], [595, 127]]}, {"minutiae": [[589, 151], [589, 163]]}, {"minutiae": [[589, 248], [592, 243]]}, {"minutiae": [[590, 264], [591, 272]]}, {"minutiae": [[591, 272], [601, 215]]}, {"minutiae": [[592, 292], [594, 296]]}, {"minutiae": [[592, 307], [594, 296]]}, {"minutiae": [[592, 307], [596, 295]]}, {"minutiae": [[593, 366], [598, 340]]}, {"minutiae": [[594, 172], [594, 174]]}, {"minutiae": [[594, 296], [596, 295]]}, {"minutiae": [[595, 127], [599, 189]]}, {"minutiae": [[595, 335], [596, 329]]}, {"minutiae": [[596, 295], [600, 285]]}, {"minutiae": [[596, 329], [597, 327]]}, {"minutiae": [[596, 329], [598, 331]]}, {"minutiae": [[596, 340], [598, 340]]}, {"minutiae": [[597, 79], [601, 103]]}, {"minutiae": [[597, 199], [599, 189]]}, {"minutiae": [[597, 199], [601, 211]]}, {"minutiae": [[597, 199], [600, 199]]}, {"minutiae": [[597, 327], [599, 321]]}, {"minutiae": [[597, 327], [598, 331]]}, {"minutiae": [[598, 331], [598, 340]]}, {"minutiae": [[599, 189], [600, 199]]}, {"minutiae": [[599, 321], [622, 258]]}, {"minutiae": [[599, 321], [602, 323]]}, {"minutiae": [[599, 366], [613, 333]]}, {"minutiae": [[600, 106], [601, 103]]}, {"minutiae": [[600, 199], [601, 211]]}, {"minutiae": [[600, 285], [604, 270]]}, {"minutiae": [[600, 285], [604, 270]]}, {"minutiae": [[601, 103], [602, 105]]}, {"minutiae": [[601, 211], [601, 215]]}, {"minutiae": [[601, 215], [604, 216]]}, {"minutiae": [[604, 270], [612, 240]]}, {"minutiae": [[605, 174], [606, 174]]}, {"minutiae": [[605, 186], [606, 174]]}, {"minutiae": [[606, 144], [609, 144]]}, {"minutiae": [[606, 174], [609, 144]]}, {"minutiae": [[606, 334], [610, 326]]}, {"minutiae": [[607, 375], [613, 366]]}, {"minutiae": [[608, 198], [610, 190]]}, {"minutiae": [[608, 225], [611, 215]]}, {"minutiae": [[608, 390], [612, 384]]}, {"minutiae": [[608, 392], [610, 402]]}, {"minutiae": [[609, 98], [611, 98]]}, {"minutiae": [[609, 144], [611, 98]]}, {"minutiae": [[609, 184], [610, 181]]}, {"minutiae": [[610, 232], [612, 236]]}, {"minutiae": [[610, 326], [619, 305]]}, {"minutiae": [[610, 326], [613, 333]]}, {"minutiae": [[610, 352], [615, 348]]}, {"minutiae": [[610, 408], [612, 406]]}, {"minutiae": [[611, 98], [612, 85]]}, {"minutiae": [[611, 215], [612, 216]]}, {"minutiae": [[611, 215], [612, 202]]}, {"minutiae": [[612, 178], [612, 180]]}, {"minutiae": [[612, 384], [615, 376]]}, {"minutiae": [[612, 384], [617, 391]]}, {"minutiae": [[613, 333], [619, 305]]}, {"minutiae": [[613, 366], [615, 348]]}, {"minutiae": [[613, 366], [615, 376]]}, {"minutiae": [[615, 167], [621, 153]]}, {"minutiae": [[615, 348], [621, 341]]}, {"minutiae": [[615, 376], [618, 376]]}, {"minutiae": [[615, 403], [617, 391]]}, {"minutiae": [[617, 391], [618, 387]]}, {"minutiae": [[619, 127], [626, 89]]}, {"minutiae": [[619, 305], [624, 296]]}, {"minutiae": [[620, 132], [622, 138]]}, {"minutiae": [[620, 252], [622, 258]]}, {"minutiae": [[621, 153], [622, 138]]}, {"minutiae": [[621, 153], [623, 159]]}, {"minutiae": [[621, 341], [629, 328]]}, {"minutiae": [[621, 341], [622, 343]]}, {"minutiae": [[622, 138], [626, 129]]}, {"minutiae": [[622, 258], [624, 256]]}, {"minutiae": [[622, 361], [625, 346]]}, {"minutiae": [[622, 374], [624, 368]]}, {"minutiae": [[624, 296], [626, 288]]}, {"minutiae": [[624, 296], [626, 299]]}, {"minutiae": [[624, 388], [626, 388]]}, {"minutiae": [[626, 85], [626, 89]]}, {"minutiae": [[626, 89], [628, 90]]}, {"minutiae": [[626, 119], [626, 127]]}, {"minutiae": [[626, 288], [627, 276]]}, {"minutiae": [[626, 288], [630, 288]]}, {"minutiae": [[626, 388], [631, 373]]}, {"minutiae": [[626, 388], [627, 394]]}, {"minutiae": [[628, 112], [631, 112]]}, {"minutiae": [[629, 328], [636, 296]]}, {"minutiae": [[629, 328], [635, 321]]}, {"minutiae": [[630, 369], [635, 334]]}, {"minutiae": [[630, 369], [630, 371]]}, {"minutiae": [[630, 369], [630, 371]]}, {"minutiae": [[630, 371], [631, 373]]}, {"minutiae": [[631, 112], [631, 115]]}, {"minutiae": [[631, 112], [635, 92]]}, {"minutiae": [[631, 373], [635, 371]]}, {"minutiae": [[633, 391], [635, 384]]}, {"minutiae": [[636, 296], [637, 292]]}, {"minutiae": [[636, 296], [638, 299]]}, {"minutiae": [[637, 286], [637, 287]]}, {"minutiae": [[640, 388], [640, 391]]}]}